Workbook

Sheet from Swathis' report
A3: Count of enrollee_id | B3: Column Labels
A4: Row Labels | B4: Cancelled | C4: Enrolled | D4: Pend | E4: Pend canceled | F4: Pending | G4: Terminated | H4: Grand Total
A5: In Selma's report | B5: 352 | C5: 888 | F5: 10 | G5: 266 | H5: 1516
A6: Not in Selma's report | B6: 115 | C6: 90 | D6: 1 | E6: 5 | F6: 15 | G6: 22 | H6: 248
A7: Grand Total | B7: 467 | C7: 978 | D7: 1 | E7: 5 | F7: 25 | G7: 288 | H7: 1764

Sheet Swathi
A1: coverage_year | B1: GAA_Load_Datetime | C1: household_id | D1: fpl | E1: ssap_application_id | F1: external_application_id | G1: application_type | H1: source | I1: application_status | J1: Insurance_Type | K1: enrollment_id | L1: enrollee_id | M1: M ID in Selma's? | N1: M ID in Selma's report status | O1: person_type | P1: relationship_type | Q1: consumer_category | R1: birth_date | S1: enrollee_first_name | T1: enrollee_last_name | U1: total_indv_responsibility_amt | V1: gross_premium_amt | W1: net_premium_amt | X1: aptc_amt | Y1: csr_amt | Z1: exchange_eligibility_status | AA1: plan_level_combined_bronze | AB1: cms_plan_id | AC1: plan_id | AD1: plan_name | AE1: hios_issuer_id | AF1: insurer_name | AG1: age | AH1: email_address | AI1: phone_number | AJ1: rating_area | AK1: county | AL1: zip | AM1: broker_role | AN1: broker_id | AO1: assister_broker_id | AP1: npn | AQ1: first_name | AR1: last_name | AS1: business_name | AT1: technology_provider | AU1: enrollment_status_description | AV1: enrollee_status_description | AW1: benefit_effective_date | AX1: benefit_end_date | AY1: enrollment_confirmation_date | AZ1: enrollment_create_date | BA1: enrollment_last_update_date | BB1: enrollee_start_date | BC1: enrollee_end_date | BD1: enrollee_create_date | BE1: enrollee_last_update_date | BF1: application_create_date | BG1: application_last_update_date
A2: 2026 | B2: 46204 | C2: 1260196 | D2: 272.23 | E2: 7775808 | F2: NULL | G2: OE | H2: ON | I2: EN | J2: Dental | K2: 212041452 | L2: 1002394459 | M2: =VLOOKUP(L2,Selma!H$1:H$3913,1,FALSE) -> 1002394459 | N2: In Selma's report | O2: Subscriber | P2: Spouse | Q2: New Consumer | R2: 32315 | S2: Kristin | T2: Hahlbohn | U2: 44.77 | V2: 44.77 | W2: 44.77 | X2: 0 | Y2: NULL | Z2: APTC | AA2: HIGH | AB2: 83502GA002000301 | AC2: 3631 | AD2: Best Life Superior Dental Plan | AE2: 83502 | AF2: BEST Life and Health Insurance Company | AG2: 37 | AH2: kahahlbohn@gmail.com | AI2: 4045940517 | AJ2: 3 | AK2: Cobb | AL2: 30064 | AM2: NULL | AN2: NULL | AO2: NULL | AP2: NULL | AQ2: NULL | AR2: NULL | AS2: NULL | AT2: NULL | AU2: Cancelled | AV2: Cancelled | AW2: 46023 | AX2: 46023 | AY2: NULL | AZ2: 46006 | BA2: 46065 | BB2: 46023 | BC2: 46023 | BD2: 46006 | BE2: 46065 | BF2: 46006 | BG2: 46065
A3: 2026 | B3: 46204 | C3: 31838 | D3: NULL | E3: 6865339 | F3: 5178101845 | G3: SEP | H3: ON | I3: EN | J3: Dental | K3: 211037564 | L3: 1000052655 | M3: =VLOOKUP(L3,Selma!H$1:H$3913,1,FALSE) -> 1000052655 | N3: In Selma's report | O3: Subscriber | P3: Spouse | Q3: Active Re-enrollee | R3: 23511 | S3: Rebecca | T3: Safon | U3: 20.37 | V3: 20.37 | W3: 20.37 | X3: NULL | Y3: NULL | Z3: QHP | AA3: LOW | AB3: 83502GA002000801 | AC3: 3634 | AD3: Best Life Essential Basic Dental Plan | AE3: 83502 | AF3: BEST Life and Health Insurance Company | AG3: 61 | AH3: safonscot@gmail.com | AI3: 6784279288 | AJ3: 3 | AK3: FULTON | AL3: 30312 | AM3: AGENT | AN3: 1312636 | AO3: 1312636 | AP3: 21576872 | AQ3: Muhammad | AR3: Naseem | AS3: NULL | AT3: NULL | AU3: Enrolled | AV3: Enrolled | AW3: 46023 | AX3: 46387 | AY3: 45946 | AZ3: 45946 | BA3: 45966 | BB3: 46023 | BC3: 46387 | BD3: 45946 | BE3: 45966 | BF3: 45966 | BG3: 46002
A4: 2026 | B4: 46204 | C4: 309257 | D4: NULL | E4: 6015636 | F4: 5150702036 | G4: OE | H4: CN | I4: EN | J4: Dental | K4: 211183913 | L4: 1000512462 | M4: =VLOOKUP(L4,Selma!H$1:H$3913,1,FALSE) -> #N/A | N4: Not in Selma's report | O4: Enrollee | P4: Child | Q4: Automatic Re-enrollee | R4: 36800 | S4: Peter | T4: Yoon | U4: 41.9 | V4: 215.24 | W4: 215.24 | X4: NULL | Y4: NULL | Z4: QHP | AA4: HIGH | AB4: 83502GA002000301 | AC4: 3631 | AD4: Best Life Superior Dental Plan | AE4: 83502 | AF4: BEST Life and Health Insurance Company | AG4: 25 | AH4: jackwyoon@gmail.com | AI4: 6783371048 | AJ4: 3 | AK4: Gwinnett | AL4: 30518 | AM4: AGENT | AN4: 10293 | AO4: 10293 | AP4: 18436232 | AQ4: ELLICE | AR4: LEE | AS4: HealthSherpa | AT4: HealthSherpa | AU4: Enrolled | AV4: Enrolled | AW4: 46023 | AX4: 46387 | AY4: 45946 | AZ4: 45946 | BA4: 46059 | BB4: 46023 | BC4: 46387 | BD4: 45946 | BE4: 46059 | BF4: 45934 | BG4: 46008
A5: 2026 | B5: 46204 | C5: 309257 | D5: NULL | E5: 6015636 | F5: 5150702036 | G5: OE | H5: CN | I5: EN | J5: Dental | K5: 211183913 | L5: 1000512461 | M5: =VLOOKUP(L5,Selma!H$1:H$3913,1,FALSE) -> #N/A | N5: Not in Selma's report | O5: Enrollee | P5: Child | Q5: Automatic Re-enrollee | R5: 37887 | S5: Jennifer | T5: Yoon | U5: 41.9 | V5: 215.24 | W5: 215.24 | X5: NULL | Y5: NULL | Z5: QHP | AA5: HIGH | AB5: 83502GA002000301 | AC5: 3631 | AD5: Best Life Superior Dental Plan | AE5: 83502 | AF5: BEST Life and Health Insurance Company | AG5: 22 | AH5: jackwyoon@gmail.com | AI5: 6783371048 | AJ5: 3 | AK5: Gwinnett | AL5: 30518 | AM5: AGENT | AN5: 10293 | AO5: 10293 | AP5: 18436232 | AQ5: ELLICE | AR5: LEE | AS5: HealthSherpa | AT5: HealthSherpa | AU5: Enrolled | AV5: Enrolled | AW5: 46023 | AX5: 46387 | AY5: 45946 | AZ5: 45946 | BA5: 46059 | BB5: 46023 | BC5: 46387 | BD5: 45946 | BE5: 46059 | BF5: 45934 | BG5: 46008
A6: 2026 | B6: 46204 | C6: 309257 | D6: NULL | E6: 6015636 | F6: 5150702036 | G6: OE | H6: CN | I6: EN | J6: Dental | K6: 211183913 | L6: 1000512464 | M6: =VLOOKUP(L6,Selma!H$1:H$3913,1,FALSE) -> #N/A | N6: Not in Selma's report | O6: Enrollee | P6: Child | Q6: Automatic Re-enrollee | R6: 38533 | S6: Brian | T6: Yoon | U6: 41.9 | V6: 215.24 | W6: 215.24 | X6: NULL | Y6: NULL | Z6: QHP | AA6: HIGH | AB6: 83502GA002000301 | AC6: 3631 | AD6: Best Life Superior Dental Plan | AE6: 83502 | AF6: BEST Life and Health Insurance Company | AG6: 20 | AH6: jackwyoon@gmail.com | AI6: 6783371048 | AJ6: 3 | AK6: Gwinnett | AL6: 30518 | AM6: AGENT | AN6: 10293 | AO6: 10293 | AP6: 18436232 | AQ6: ELLICE | AR6: LEE | AS6: HealthSherpa | AT6: HealthSherpa | AU6: Enrolled | AV6: Enrolled | AW6: 46023 | AX6: 46387 | AY6: 45946 | AZ6: 45946 | BA6: 46059 | BB6: 46023 | BC6: 46387 | BD6: 45946 | BE6: 46059 | BF6: 45934 | BG6: 46008
A7: 2026 | B7: 46204 | C7: 309257 | D7: NULL | E7: 6015636 | F7: 5150702036 | G7: OE | H7: CN | I7: EN | J7: Dental | K7: 211183913 | L7: 1000512463 | M7: =VLOOKUP(L7,Selma!H$1:H$3913,1,FALSE) -> #N/A | N7: Not in Selma's report | O7: Enrollee | P7: Spouse | Q7: Automatic Re-enrollee | R7: 27129 | S7: Annie | T7: Jung | U7: 44.77 | V7: 215.24 | W7: 215.24 | X7: NULL | Y7: NULL | Z7: QHP | AA7: HIGH | AB7: 83502GA002000301 | AC7: 3631 | AD7: Best Life Superior Dental Plan | AE7: 83502 | AF7: BEST Life and Health Insurance Company | AG7: 51 | AH7: jackwyoon@gmail.com | AI7: 6783371048 | AJ7: 3 | AK7: Gwinnett | AL7: 30518 | AM7: AGENT | AN7: 10293 | AO7: 10293 | AP7: 18436232 | AQ7: ELLICE | AR7: LEE | AS7: HealthSherpa | AT7: HealthSherpa | AU7: Enrolled | AV7: Enrolled | AW7: 46023 | AX7: 46387 | AY7: 45946 | AZ7: 45946 | BA7: 46059 | BB7: 46023 | BC7: 46387 | BD7: 45946 | BE7: 46059 | BF7: 45934 | BG7: 46008
A8: 2026 | B8: 46204 | C8: 309257 | D8: NULL | E8: 6015636 | F8: 5150702036 | G8: OE | H8: CN | I8: EN | J8: Dental | K8: 211183913 | L8: 1000512465 | M8: =VLOOKUP(L8,Selma!H$1:H$3913,1,FALSE) -> #N/A | N8: Not in Selma's report | O8: Subscriber | P8: Self | Q8: Automatic Re-enrollee | R8: 24880 | S8: Jack | T8: Yoon | U8: 44.77 | V8: 215.24 | W8: 215.24 | X8: NULL | Y8: NULL | Z8: QHP | AA8: HIGH | AB8: 83502GA002000301 | AC8: 3631 | AD8: Best Life Superior Dental Plan | AE8: 83502 | AF8: BEST Life and Health Insurance Company | AG8: 57 | AH8: jackwyoon@gmail.com | AI8: 6783371048 | AJ8: 3 | AK8: Gwinnett | AL8: 30518 | AM8: AGENT | AN8: 10293 | AO8: 10293 | AP8: 18436232 | AQ8: ELLICE | AR8: LEE | AS8: HealthSherpa | AT8: HealthSherpa | AU8: Enrolled | AV8: Enrolled | AW8: 46023 | AX8: 46387 | AY8: 45946 | AZ8: 45946 | BA8: 46059 | BB8: 46023 | BC8: 46387 | BD8: 45946 | BE8: 46059 | BF8: 45934 | BG8: 46008
A9: 2026 | B9: 46204 | C9: 381682 | D9: 0 | E9: 5791787 | F9: 5412252607 | G9: OE | H9: CN | I9: EN | J9: Dental | K9: 211537282 | L9: 1000631776 | M9: =VLOOKUP(L9,Selma!H$1:H$3913,1,FALSE) -> 1000631776 | N9: In Selma's report | O9: Subscriber | P9: Self | Q9: Active Re-enrollee | R9: 35843 | S9: Charles | T9: Franklin | U9: 36.67 | V9: 36.67 | W9: 36.67 | X9: NULL | Y9: NULL | Z9: QHP | AA9: HIGH | AB9: 83502GA002000701 | AC9: 3633 | AD9: Best Life Preferred Dental Plan | AE9: 83502 | AF9: BEST Life and Health Insurance Company | AG9: 27 | AH9: colefranklin217@yahoo.com | AI9: 4044529086 | AJ9: 3 | AK9: COBB | AL9: 30101 | AM9: AGENT | AN9: 551626 | AO9: 551626 | AP9: 1262563 | AQ9: JOSEPH JOHN | AR9: CHVATAL | AS9: NULL | AT9: NULL | AU9: Enrolled | AV9: Enrolled | AW9: 46023 | AX9: 46387 | AY9: 45947 | AZ9: 45947 | BA9: 45947 | BB9: 46023 | BC9: 46387 | BD9: 45947 | BE9: 45947 | BF9: 45934 | BG9: 46013
A10: 2026 | B10: 46204 | C10: 383743 | D10: NULL | E10: 8246472 | F10: 5153844815 | G10: SEP | H10: ON | I10: EN | J10: Dental | K10: 211051916 | L10: 1000635444 | M10: =VLOOKUP(L10,Selma!H$1:H$3913,1,FALSE) -> 1000635444 | N10: In Selma's report | O10: Subscriber | P10: Spouse | Q10: Automatic Re-enrollee | R10: 23795 | S10: Beverly | T10: Holman | U10: 22.01 | V10: 22.01 | W10: 22.01 | X10: NULL | Y10: NULL | Z10: QHP | AA10: LOW | AB10: 83502GA002000601 | AC10: 3632 | AD10: Best Life Essential Value Dental Plan | AE10: 83502 | AF10: BEST Life and Health Insurance Company | AG10: 60 | AH10: bholman124@yahoo.com | AI10: 5107145154 | AJ10: 10 | AK10: HALL | AL10: 30542 | AM10: AGENT | AN10: 548527 | AO10: 548527 | AP10: 9126142 | AQ10: BRENDA J | AR10: GONZALEZ | AS10: NULL | AT10: NULL | AU10: Enrolled | AV10: Enrolled | AW10: 46023 | AX10: 46387 | AY10: 45946 | AZ10: 45946 | BA10: 46042 | BB10: 46023 | BC10: 46387 | BD10: 45946 | BE10: 46042 | BF10: 46042 | BG10: 46042
A11: 2026 | B11: 46204 | C11: 581489 | D11: NULL | E11: 8976698 | F11: 5154574740 | G11: SEP | H11: RR | I11: EN | J11: Dental | K11: 1000128793 | L11: 1000963464 | M11: =VLOOKUP(L11,Selma!H$1:H$3913,1,FALSE) -> #N/A | N11: Not in Selma's report | O11: Subscriber | P11: Self | Q11: Active Re-enrollee | R11: 31308 | S11: Anthony | T11: Smith | U11: 44.77 | V11: 44.77 | W11: 44.77 | X11: NULL | Y11: NULL | Z11: QHP | AA11: HIGH | AB11: 83502GA002000301 | AC11: 3631 | AD11: Best Life Superior Dental Plan | AE11: 83502 | AF11: BEST Life and Health Insurance Company | AG11: 40 | AH11: djlilant119@gmail.com | AI11: 4047801362 | AJ11: 3 | AK11: Henry | AL11: 30253 | AM11: AGENT | AN11: 873610 | AO11: 873610 | AP11: 21343326 | AQ11: Yessenya | AR11: Sanchez Hernandez | AS11: HealthSherpa | AT11: HealthSherpa | AU11: Cancelled | AV11: Cancelled | AW11: 46113 | AX11: 46113 | AY11: NULL | AZ11: 46106 | BA11: 46130 | BB11: 46113 | BC11: 46113 | BD11: 46106 | BE11: 46129 | BF11: 46130 | BG11: 46130
A12: 2026 | B12: 46204 | C12: 650866 | D12: NULL | E12: 7677354 | F12: 5137647580 | G12: OE | H12: EDE | I12: EN | J12: Dental | K12: 211308422 | L12: 1001078511 | M12: =VLOOKUP(L12,Selma!H$1:H$3913,1,FALSE) -> 1001078511 | N12: In Selma's report | O12: Subscriber | P12: Self | Q12: Active Re-enrollee | R12: 25327 | S12: Melinda | T12: Beatenbough | U12: 44.77 | V12: 131.44 | W12: 131.44 | X12: NULL | Y12: NULL | Z12: QHP | AA12: HIGH | AB12: 83502GA002000301 | AC12: 3631 | AD12: Best Life Superior Dental Plan | AE12: 83502 | AF12: BEST Life and Health Insurance Company | AG12: 56 | AH12: mindi.beat@gmail.com | AI12: 4047879642 | AJ12: 3 | AK12: Clayton | AL12: 30236 | AM12: AGENT | AN12: 548378 | AO12: 548378 | AP12: 19816672 | AQ12: BENIA | AR12: RENE | AS12: Centene-Ambetter | AT12: HealthSherpa | AU12: Cancelled | AV12: Cancelled | AW12: 46023 | AX12: 46023 | AY12: 45947 | AZ12: 45947 | BA12: 46003 | BB12: 46023 | BC12: 46023 | BD12: 45947 | BE12: 46003 | BF12: 46003 | BG12: 46003
A13: 2026 | B13: 46204 | C13: 683835 | D13: NULL | E13: 7491604 | F13: 5128928188 | G13: SEP | H13: ON | I13: EN | J13: Dental | K13: 212106737 | L13: 1001133291 | M13: =VLOOKUP(L13,Selma!H$1:H$3913,1,FALSE) -> 1001133291 | N13: In Selma's report | O13: Subscriber | P13: Self | Q13: Active Re-enrollee | R13: 27263 | S13: AZIZ | T13: DAMANI | U13: 44.77 | V13: 131.44 | W13: 131.44 | X13: NULL | Y13: NULL | Z13: QHP | AA13: HIGH | AB13: 83502GA002000301 | AC13: 3631 | AD13: Best Life Superior Dental Plan | AE13: 83502 | AF13: BEST Life and Health Insurance Company | AG13: 51 | AH13: aziz@damaniholdings.com | AI13: 4047757986 | AJ13: 3 | AK13: GWINNETT | AL13: 30097 | AM13: AGENT | AN13: 552558 | AO13: 552558 | AP13: 8184400 | AQ13: MELISSA J | AR13: COCHRAN | AS13: NULL | AT13: NULL | AU13: Terminated | AV13: Terminated | AW13: 46023 | AX13: 46081 | AY13: 46031 | AZ13: 46015 | BA13: 46124 | BB13: 46023 | BC13: 46081 | BD13: 46015 | BE13: 46124 | BF13: 45994 | BG13: 46015
A14: 2026 | B14: 46204 | C14: 683835 | D14: NULL | E14: 7491604 | F14: 5128928188 | G14: SEP | H14: ON | I14: EN | J14: Dental | K14: 212106737 | L14: 1001133292 | M14: =VLOOKUP(L14,Selma!H$1:H$3913,1,FALSE) -> 1001133292 | N14: In Selma's report | O14: Enrollee | P14: Spouse | Q14: Active Re-enrollee | R14: 28038 | S14: SONIA | T14: DAMANI | U14: 44.77 | V14: 131.44 | W14: 131.44 | X14: NULL | Y14: NULL | Z14: QHP | AA14: HIGH | AB14: 83502GA002000301 | AC14: 3631 | AD14: Best Life Superior Dental Plan | AE14: 83502 | AF14: BEST Life and Health Insurance Company | AG14: 49 | AH14: aziz@damaniholdings.com | AI14: 4047757986 | AJ14: 3 | AK14: GWINNETT | AL14: 30097 | AM14: AGENT | AN14: 552558 | AO14: 552558 | AP14: 8184400 | AQ14: MELISSA J | AR14: COCHRAN | AS14: NULL | AT14: NULL | AU14: Terminated | AV14: Terminated | AW14: 46023 | AX14: 46081 | AY14: 46031 | AZ14: 46015 | BA14: 46124 | BB14: 46023 | BC14: 46081 | BD14: 46015 | BE14: 46124 | BF14: 45994 | BG14: 46015
A15: 2026 | B15: 46204 | C15: 683835 | D15: NULL | E15: 7491604 | F15: 5128928188 | G15: SEP | H15: ON | I15: EN | J15: Dental | K15: 212106737 | L15: 1001133293 | M15: =VLOOKUP(L15,Selma!H$1:H$3913,1,FALSE) -> 1001133293 | N15: In Selma's report | O15: Enrollee | P15: Child | Q15: Active Re-enrollee | R15: 38554 | S15: AMAR | T15: DAMANI | U15: 41.9 | V15: 131.44 | W15: 131.44 | X15: NULL | Y15: NULL | Z15: QHP | AA15: HIGH | AB15: 83502GA002000301 | AC15: 3631 | AD15: Best Life Superior Dental Plan | AE15: 83502 | AF15: BEST Life and Health Insurance Company | AG15: 20 | AH15: aziz@damaniholdings.com | AI15: 4047757986 | AJ15: 3 | AK15: GWINNETT | AL15: 30097 | AM15: AGENT | AN15: 552558 | AO15: 552558 | AP15: 8184400 | AQ15: MELISSA J | AR15: COCHRAN | AS15: NULL | AT15: NULL | AU15: Terminated | AV15: Terminated | AW15: 46023 | AX15: 46081 | AY15: 46031 | AZ15: 46015 | BA15: 46124 | BB15: 46023 | BC15: 46081 | BD15: 46015 | BE15: 46124 | BF15: 45994 | BG15: 46015
A16: 2026 | B16: 46204 | C16: 693469 | D16: 0 | E16: 8275604 | F16: GAT123003925 | G16: SEP | H16: ON | I16: PN | J16: Dental | K16: 212260531 | L16: 1001148905 | M16: =VLOOKUP(L16,Selma!H$1:H$3913,1,FALSE) -> #N/A | N16: Not in Selma's report | O16: Subscriber | P16: Self | Q16: Active Re-enrollee | R16: 34851 | S16: TABITHA | T16: SMITH | U16: 17.17 | V16: 17.17 | W16: 17.17 | X16: NULL | Y16: NULL | Z16: QHP | AA16: LOW | AB16: 83502GA002000801 | AC16: 3634 | AD16: Best Life Essential Basic Dental Plan | AE16: 83502 | AF16: BEST Life and Health Insurance Company | AG16: 30 | AH16: lilbitbit7970@gmail.com | AI16: 4782835787 | AJ16: 12 | AK16: Bibb | AL16: 31206 | AM16: AGENT | AN16: 9371 | AO16: 9371 | AP16: 20546556 | AQ16: RENE | AR16: NARANJO | AS16: HealthSherpa | AT16: HealthSherpa | AU16: Cancelled | AV16: Cancelled | AW16: 46054 | AX16: 46054 | AY16: NULL | AZ16: 46046 | BA16: 46046 | BB16: 46054 | BC16: 46054 | BD16: 46046 | BE16: 46046 | BF16: 46045 | BG16: 46046
A17: 2026 | B17: 46204 | C17: 756034 | D17: NULL | E17: 7098384 | F17: 5171948999 | G17: SEP | H17: ON | I17: EN | J17: Dental | K17: 210574895 | L17: 1001252609 | M17: =VLOOKUP(L17,Selma!H$1:H$3913,1,FALSE) -> 1001252609 | N17: In Selma's report | O17: Subscriber | P17: Self | Q17: Active Re-enrollee | R17: 26942 | S17: Charles | T17: Franklin | U17: 36.67 | V17: 36.67 | W17: 36.67 | X17: NULL | Y17: NULL | Z17: QHP | AA17: HIGH | AB17: 83502GA002000701 | AC17: 3633 | AD17: Best Life Preferred Dental Plan | AE17: 83502 | AF17: BEST Life and Health Insurance Company | AG17: 52 | AH17: franklinc37@yahoo.com | AI17: 7706161697 | AJ17: 3 | AK17: COBB | AL17: 30101 | AM17: AGENT | AN17: 551626 | AO17: 551626 | AP17: 1262563 | AQ17: JOSEPH JOHN | AR17: CHVATAL | AS17: NULL | AT17: NULL | AU17: Terminated | AV17: Terminated | AW17: 46023 | AX17: 46203 | AY17: 45946 | AZ17: 45946 | BA17: 46188 | BB17: 46023 | BC17: 46203 | BD17: 45946 | BE17: 46188 | BF17: 45981 | BG17: 46009
A18: 2026 | B18: 46204 | C18: 890265 | D18: 0 | E18: 8425250 | F18: 5168583477 | G18: SEP | H18: ON | I18: PN | J18: Dental | K18: 1000118019 | L18: 1001475165 | M18: =VLOOKUP(L18,Selma!H$1:H$3913,1,FALSE) -> #N/A | N18: Not in Selma's report | O18: Subscriber | P18: Self | Q18: Automatic Re-enrollee | R18: 25892 | S18: Catherine | T18: Archer | U18: 44.77 | V18: 44.77 | W18: 44.77 | X18: NULL | Y18: NULL | Z18: QHP | AA18: HIGH | AB18: 83502GA002000301 | AC18: 3631 | AD18: Best Life Superior Dental Plan | AE18: 83502 | AF18: BEST Life and Health Insurance Company | AG18: 55 | AH18: catarcher3@yahoo.com | AI18: 4706302442 | AJ18: 3 | AK18: Bartow | AL18: 30120 | AM18: AGENT | AN18: 720 | AO18: 720 | AP18: 18205745 | AQ18: PAOLA | AR18: FRITZ | AS18: HealthSherpa | AT18: HealthSherpa | AU18: Cancelled | AV18: Cancelled | AW18: 46113 | AX18: 46113 | AY18: NULL | AZ18: 46101 | BA18: 46104 | BB18: 46113 | BC18: 46113 | BD18: 46101 | BE18: 46104 | BF18: 46061 | BG18: 46141
A19: 2026 | B19: 46204 | C19: 937417 | D19: NULL | E19: 5928881 | F19: 5175937903 | G19: OE | H19: CN | I19: EN | J19: Dental | K19: 211519809 | L19: 1001553377 | M19: =VLOOKUP(L19,Selma!H$1:H$3913,1,FALSE) -> 1001553377 | N19: In Selma's report | O19: Enrollee | P19: Spouse | Q19: Automatic Re-enrollee | R19: 28089 | S19: Donna | T19: Johnson | U19: 38.23 | V19: 76.46 | W19: 76.46 | X19: NULL | Y19: NULL | Z19: QHP | AA19: HIGH | AB19: 83502GA002000301 | AC19: 3631 | AD19: Best Life Superior Dental Plan | AE19: 83502 | AF19: BEST Life and Health Insurance Company | AG19: 49 | AH19: jwms.andy@gmail.com | AI19: 9122222210 | AJ19: 6 | AK19: GLYNN | AL19: 31523 | AM19: AGENT | AN19: 4854 | AO19: 4854 | AP19: 17410092 | AQ19: TRICE | AR19: THORNTON | AS19: NULL | AT19: NULL | AU19: Enrolled | AV19: Enrolled | AW19: 46023 | AX19: 46387 | AY19: 45947 | AZ19: 45947 | BA19: 45947 | BB19: 46023 | BC19: 46387 | BD19: 45947 | BE19: 45947 | BF19: 45934 | BG19: 45947
A20: 2026 | B20: 46204 | C20: 937417 | D20: NULL | E20: 5928881 | F20: 5175937903 | G20: OE | H20: CN | I20: EN | J20: Dental | K20: 211519809 | L20: 1001553376 | M20: =VLOOKUP(L20,Selma!H$1:H$3913,1,FALSE) -> 1001553376 | N20: In Selma's report | O20: Subscriber | P20: Self | Q20: Automatic Re-enrollee | R20: 26841 | S20: Andrew | T20: Johnson | U20: 38.23 | V20: 76.46 | W20: 76.46 | X20: NULL | Y20: NULL | Z20: QHP | AA20: HIGH | AB20: 83502GA002000301 | AC20: 3631 | AD20: Best Life Superior Dental Plan | AE20: 83502 | AF20: BEST Life and Health Insurance Company | AG20: 52 | AH20: jwms.andy@gmail.com | AI20: 9122222210 | AJ20: 6 | AK20: GLYNN | AL20: 31523 | AM20: AGENT | AN20: 4854 | AO20: 4854 | AP20: 17410092 | AQ20: TRICE | AR20: THORNTON | AS20: NULL | AT20: NULL | AU20: Enrolled | AV20: Enrolled | AW20: 46023 | AX20: 46387 | AY20: 45947 | AZ20: 45947 | BA20: 45947 | BB20: 46023 | BC20: 46387 | BD20: 45947 | BE20: 45947 | BF20: 45934 | BG20: 45947
A21: 2026 | B21: 46204 | C21: 1013137 | D21: NULL | E21: 6990522 | F21: 5236386575 | G21: OE | H21: EDE | I21: EN | J21: Dental | K21: 210983425 | L21: 1001679105 | M21: =VLOOKUP(L21,Selma!H$1:H$3913,1,FALSE) -> 1001679105 | N21: In Selma's report | O21: Subscriber | P21: Self | Q21: Active Re-enrollee | R21: 31875 | S21: Richard | T21: Holtzman | U21: 20.37 | V21: 20.37 | W21: 20.37 | X21: NULL | Y21: NULL | Z21: QHP | AA21: LOW | AB21: 83502GA002000801 | AC21: 3634 | AD21: Best Life Essential Basic Dental Plan | AE21: 83502 | AF21: BEST Life and Health Insurance Company | AG21: 38 | AH21: richieholtzman@gmail.com | AI21: 7703773818 | AJ21: 3 | AK21: Fulton | AL21: 30075 | AM21: AGENT | AN21: 4466 | AO21: 4466 | AP21: 20389330 | AQ21: JOEL | AR21: FULGHUM | AS21: HealthSherpa | AT21: HealthSherpa | AU21: Enrolled | AV21: Enrolled | AW21: 46023 | AX21: 46387 | AY21: 45946 | AZ21: 45946 | BA21: 45974 | BB21: 46023 | BC21: 46387 | BD21: 45946 | BE21: 45974 | BF21: 45974 | BG21: 45974
A22: 2026 | B22: 46204 | C22: 1060766 | D22: 0 | E22: 8680945 | F22: NULL | G22: SEP | H22: RR | I22: EN | J22: Dental | K22: 212185644 | L22: 1001796137 | M22: =VLOOKUP(L22,Selma!H$1:H$3913,1,FALSE) -> 1001796137 | N22: In Selma's report | O22: Subscriber | P22: Self | Q22: Automatic Re-enrollee | R22: 36684 | S22: Mary | T22: Austin | U22: 29.32 | V22: 29.32 | W22: 29.32 | X22: NULL | Y22: NULL | Z22: QHP | AA22: HIGH | AB22: 83502GA002000701 | AC22: 3633 | AD22: Best Life Preferred Dental Plan | AE22: 83502 | AF22: BEST Life and Health Insurance Company | AG22: 25 | AH22: marymac060700@gmail.com | AI22: 7064363928 | AJ22: 10 | AK22: Hart | AL22: 30643 | AM22: AGENT | AN22: 5773 | AO22: 5773 | AP22: 20567974 | AQ22: STEPHEN | AR22: SMITH | AS22: HealthSherpa | AT22: HealthSherpa | AU22: Cancelled | AV22: Cancelled | AW22: 46054 | AX22: 46054 | AY22: NULL | AZ22: 46032 | BA22: 46094 | BB22: 46054 | BC22: 46054 | BD22: 46032 | BE22: 46094 | BF22: 46087 | BG22: 46094
A23: 2026 | B23: 46204 | C23: 2376401 | D23: NULL | E23: 9349217 | F23: NULL | G23: SEP | H23: ON | I23: EN | J23: Dental | K23: 1000028484 | L23: 1007152241 | M23: =VLOOKUP(L23,Selma!H$1:H$3913,1,FALSE) -> 1007152241 | N23: In Selma's report | O23: Subscriber | P23: Self | Q23: New Consumer | R23: 35870 | S23: Ailisha | T23: Casey | U23: 36.67 | V23: 36.67 | W23: 36.67 | X23: NULL | Y23: NULL | Z23: QHP | AA23: HIGH | AB23: 83502GA002000701 | AC23: 3633 | AD23: Best Life Preferred Dental Plan | AE23: 83502 | AF23: BEST Life and Health Insurance Company | AG23: 27 | AH23: ailishacasey@yahoo.com | AI23: 6786547693 | AJ23: 3 | AK23: Fulton | AL23: 30305 | AM23: AGENT | AN23: 554729 | AO23: 554729 | AP23: 1316142 | AQ23: EDWARD WITTWER | AR23: OFFICER | AS23: NULL | AT23: NULL | AU23: Terminated | AV23: Terminated | AW23: 46082 | AX23: 46142 | AY23: 46106 | AZ23: 46065 | BA23: 46189 | BB23: 46082 | BC23: 46142 | BD23: 46065 | BE23: 46189 | BF23: 46189 | BG23: 46189
A24: 2026 | B24: 46204 | C24: 193864 | D24: 118.2 | E24: 5747101 | F24: 5422104947 | G24: OE | H24: CN | I24: EN | J24: Dental | K24: 212238524 | L24: 1000320577 | M24: =VLOOKUP(L24,Selma!H$1:H$3913,1,FALSE) -> #N/A | N24: Not in Selma's report | O24: Enrollee | P24: Child | Q24: Automatic Re-enrollee | R24: 43779 | S24: Caroline | T24: Nelson | U24: 28.77 | V24: 51.68 | W24: 51.68 | X24: NULL | Y24: NULL | Z24: APTC_CSR | AA24: LOW | AB24: 83502GA002000601 | AC24: 3632 | AD24: Best Life Essential Value Dental Plan | AE24: 83502 | AF24: BEST Life and Health Insurance Company | AG24: 6 | AH24: jacob291989@gmail.com | AI24: 7063020878 | AJ24: 8 | AK24: Troup | AL24: 30241 | AM24: AGENT | AN24: 2728 | AO24: 2728 | AP24: 17178212 | AQ24: LADALE | AR24: LANE | AS24: HealthSherpa | AT24: HealthSherpa | AU24: Cancelled | AV24: Cancelled | AW24: 46054 | AX24: 46054 | AY24: NULL | AZ24: 46037 | BA24: 46094 | BB24: 46054 | BC24: 46054 | BD24: 46037 | BE24: 46094 | BF24: 45934 | BG24: 46094
A25: 2026 | B25: 46204 | C25: 229605 | D25: 100.05 | E25: 7833010 | F25: 5145476766 | G25: OE | H25: ON | I25: EN | J25: Dental | K25: 212223856 | L25: 1000380036 | M25: =VLOOKUP(L25,Selma!H$1:H$3913,1,FALSE) -> #N/A | N25: Not in Selma's report | O25: Enrollee | P25: Child | Q25: New Consumer | R25: 38125 | S25: Cameron | T25: Pitts | U25: 35.79 | V25: 74.02 | W25: 74.02 | X25: NULL | Y25: NULL | Z25: APTC_CSR | AA25: HIGH | AB25: 83502GA002000301 | AC25: 3631 | AD25: Best Life Superior Dental Plan | AE25: 83502 | AF25: BEST Life and Health Insurance Company | AG25: 21 | AH25: pittsmobiletire@gmail.com | AI25: 2292568961 | AJ25: 1 | AK25: Sumter | AL25: 31709 | AM25: AGENT | AN25: 1736 | AO25: 1736 | AP25: 4649559 | AQ25: ANGELA | AR25: BOVELL | AS25: HealthSherpa | AT25: HealthSherpa | AU25: Cancelled | AV25: Cancelled | AW25: 46054 | AX25: 46054 | AY25: NULL | AZ25: 46037 | BA25: 46037 | BB25: 46054 | BC25: 46054 | BD25: 46037 | BE25: 46037 | BF25: 46008 | BG25: 46191
A26: 2026 | B26: 46204 | C26: 323288 | D26: 102.77 | E26: 9313815 | F26: GAT50175098 | G26: QEP | H26: EDE | I26: EN | J26: Dental | K26: 212061197 | L26: 1000534867 | M26: =VLOOKUP(L26,Selma!H$1:H$3913,1,FALSE) -> #N/A | N26: Not in Selma's report | O26: Enrollee | P26: Spouse | Q26: Active Re-enrollee | R26: 26813 | S26: Melinda | T26: Muhammad | U26: 38.98 | V26: 77.96 | W26: 77.96 | X26: NULL | Y26: NULL | Z26: APTC_CSR | AA26: HIGH | AB26: 83502GA002000301 | AC26: 3631 | AD26: Best Life Superior Dental Plan | AE26: 83502 | AF26: BEST Life and Health Insurance Company | AG26: 52 | AH26: mshaymuhammad1@gmail.com | AI26: 7064240656 | AJ26: 2 | AK26: Oglethorpe | AL26: 30669 | AM26: AGENT | AN26: 3568 | AO26: 3568 | AP26: 17366906 | AQ26: LUIS | AR26: DE LA ROSA | AS26: HealthSherpa | AT26: HealthSherpa | AU26: Cancelled | AV26: Cancelled | AW26: 46023 | AX26: 46023 | AY26: NULL | AZ26: 46006 | BA26: 46065 | BB26: 46023 | BC26: 46023 | BD26: 46006 | BE26: 46065 | BF26: 46182 | BG26: 46185
A27: 2026 | B27: 46204 | C27: 328969 | D27: 120.38 | E27: 9291722 | F27: 5167824520 | G27: SEP | H27: ON | I27: EN | J27: Dental | K27: 212034099 | L27: 1000544826 | M27: =VLOOKUP(L27,Selma!H$1:H$3913,1,FALSE) -> #N/A | N27: Not in Selma's report | O27: Enrollee | P27: Spouse | Q27: Active Re-enrollee | R27: 26415 | S27: Gerald | T27: Wesley | U27: 39.79 | V27: 79.58 | W27: 79.58 | X27: 0 | Y27: NULL | Z27: APTC_CSR | AA27: HIGH | AB27: 83502GA002000301 | AC27: 3631 | AD27: Best Life Superior Dental Plan | AE27: 83502 | AF27: BEST Life and Health Insurance Company | AG27: 53 | AH27: shanika314wesley@gmail.com | AI27: 7708758935 | AJ27: 8 | AK27: Troup | AL27: 30241 | AM27: AGENT | AN27: 8484 | AO27: 8484 | AP27: 19237196 | AQ27: NANA | AR27: NASH | AS27: HealthSherpa | AT27: HealthSherpa | AU27: Cancelled | AV27: Cancelled | AW27: 46023 | AX27: 46023 | AY27: NULL | AZ27: 46006 | BA27: 46065 | BB27: 46023 | BC27: 46023 | BD27: 46006 | BE27: 46065 | BF27: 46177 | BG27: 46177
A28: 2026 | B28: 46204 | C28: 376722 | D28: 108.82 | E28: 5635057 | F28: 5308338546 | G28: OE | H28: CN | I28: EN | J28: Dental | K28: 210659907 | L28: 1000623919 | M28: =VLOOKUP(L28,Selma!H$1:H$3913,1,FALSE) -> 1000623919 | N28: In Selma's report | O28: Enrollee | P28: Self | Q28: Active Re-enrollee | R28: 22475 | S28: Mosun | T28: Adekunle | U28: 53.72 | V28: 98.49 | W28: 98.49 | X28: NULL | Y28: NULL | Z28: APTC_CSR | AA28: HIGH | AB28: 83502GA002000301 | AC28: 3631 | AD28: Best Life Superior Dental Plan | AE28: 83502 | AF28: BEST Life and Health Insurance Company | AG28: 64 | AH28: hkmcare@pm.me | AI28: 7707224819 | AJ28: 3 | AK28: ROCKDALE | AL28: 30094 | AM28: AGENT | AN28: 548527 | AO28: 548527 | AP28: 9126142 | AQ28: BRENDA J | AR28: GONZALEZ | AS28: NULL | AT28: NULL | AU28: Cancelled | AV28: Cancelled | AW28: 46023 | AX28: 46023 | AY28: 45946 | AZ28: 45946 | BA28: 46061 | BB28: 46023 | BC28: 46023 | BD28: 45946 | BE28: 46061 | BF28: 45934 | BG28: 46061
A29: 2026 | B29: 46204 | C29: 398575 | D29: 120.57 | E29: 5801548 | F29: 5131894152 | G29: OE | H29: CN | I29: EN | J29: Dental | K29: 210631260 | L29: 1000659779 | M29: =VLOOKUP(L29,Selma!H$1:H$3913,1,FALSE) -> 1000659779 | N29: In Selma's report | O29: Enrollee | P29: Spouse | Q29: Automatic Re-enrollee | R29: 28716 | S29: Uriel | T29: Rubio Ponce | U29: 16.72 | V29: 33.44 | W29: 33.44 | X29: NULL | Y29: NULL | Z29: APTC_CSR | AA29: LOW | AB29: 83502GA002000801 | AC29: 3634 | AD29: Best Life Essential Basic Dental Plan | AE29: 83502 | AF29: BEST Life and Health Insurance Company | AG29: 47 | AH29: evelia1977@icloud.com | AI29: 7069805280 | AJ29: 9 | AK29: WHITFIELD | AL29: 30720 | AM29: AGENT | AN29: 1760344 | AO29: 1760344 | AP29: 17437412 | AQ29: Roberto | AR29: Gutierrez Plazarte | AS29: NULL | AT29: NULL | AU29: Cancelled | AV29: Cancelled | AW29: 46023 | AX29: 46023 | AY29: 45946 | AZ29: 45946 | BA29: 46190 | BB29: 46023 | BC29: 46023 | BD29: 45946 | BE29: 46190 | BF29: 45934 | BG29: 45984
A30: 2026 | B30: 46204 | C30: 430403 | D30: 106.15 | E30: 8774308 | F30: 5167749839 | G30: SEP | H30: RR | I30: EN | J30: Dental | K30: 212059681 | L30: 1000712451 | M30: =VLOOKUP(L30,Selma!H$1:H$3913,1,FALSE) -> 1000712451 | N30: In Selma's report | O30: Enrollee | P30: Spouse | Q30: Active Re-enrollee | R30: 30857 | S30: Sukhdeep | T30: Bhatti | U30: 44.77 | V30: 89.54 | W30: 89.54 | X30: NULL | Y30: NULL | Z30: APTC_CSR | AA30: HIGH | AB30: 83502GA002000301 | AC30: 3631 | AD30: Best Life Superior Dental Plan | AE30: 83502 | AF30: BEST Life and Health Insurance Company | AG30: 41 | AH30: lokhandwalasana@gmail.com | AI30: 4043339846 | AJ30: 3 | AK30: NULL | AL30: 30040 | AM30: AGENT | AN30: 9436 | AO30: 9436 | AP30: 20457319 | AQ30: CHARITY | AR30: GILLESPIE | AS30: NULL | AT30: NULL | AU30: Terminated | AV30: Terminated | AW30: 46023 | AX30: 46142 | AY30: 46032 | AZ30: 46006 | BA30: 46186 | BB30: 46023 | BC30: 46142 | BD30: 46006 | BE30: 46186 | BF30: 46100 | BG30: 46139
A31: 2026 | B31: 46204 | C31: 467246 | D31: 123.35 | E31: 7559930 | F31: 5118844799 | G31: SEP | H31: ON | I31: EN | J31: Dental | K31: 211002985 | L31: 1000773598 | M31: =VLOOKUP(L31,Selma!H$1:H$3913,1,FALSE) -> #N/A | N31: Not in Selma's report | O31: Enrollee | P31: Spouse | Q31: New Consumer | R31: 29730 | S31: Meron | T31: Debela | U31: 25.77 | V31: 51.54 | W31: 51.54 | X31: NULL | Y31: NULL | Z31: APTC_CSR | AA31: LOW | AB31: 83502GA002000601 | AC31: 3632 | AD31: Best Life Essential Value Dental Plan | AE31: 83502 | AF31: BEST Life and Health Insurance Company | AG31: 44 | AH31: aketsela@hotmail.com | AI31: 4048496808 | AJ31: 3 | AK31: GWINNETT | AL31: 30084 | AM31: AGENT | AN31: 551610 | AO31: 551610 | AP31: 17028382 | AQ31: JORGO | AR31: LEMMA | AS31: NULL | AT31: NULL | AU31: Terminated | AV31: Terminated | AW31: 46023 | AX31: 46203 | AY31: 45946 | AZ31: 45946 | BA31: 46176 | BB31: 46023 | BC31: 46203 | BD31: 46003 | BE31: 46176 | BF31: 45999 | BG31: 46003
A32: 2026 | B32: 46204 | C32: 577475 | D32: 102.9 | E32: 7523282 | F32: 5114815792 | G32: SEP | H32: ON | I32: EN | J32: Dental | K32: 210667685 | L32: 1000956338 | M32: =VLOOKUP(L32,Selma!H$1:H$3913,1,FALSE) -> 1000956338 | N32: In Selma's report | O32: Enrollee | P32: Child | Q32: Active Re-enrollee | R32: 37319 | S32: Wynter | T32: Bayne | U32: 19.07 | V32: 78.88 | W32: 78.88 | X32: NULL | Y32: NULL | Z32: APTC_CSR | AA32: LOW | AB32: 83502GA002000801 | AC32: 3634 | AD32: Best Life Essential Basic Dental Plan | AE32: 83502 | AF32: BEST Life and Health Insurance Company | AG32: 23 | AH32: bayne2girls@gmail.com | AI32: 7705978010 | AJ32: 3 | AK32: GWINNETT | AL32: 30045 | AM32: AGENT | AN32: 1176094 | AO32: 1176094 | AP32: 18924885 | AQ32: Aslynn | AR32: Peacock | AS32: HealthSherpa | AT32: HealthSherpa | AU32: Enrolled | AV32: Enrolled | AW32: 46023 | AX32: 46387 | AY32: 45946 | AZ32: 45946 | BA32: 46020 | BB32: 46023 | BC32: 46387 | BD32: 45946 | BE32: 46020 | BF32: 45996 | BG32: 46002
A33: 2026 | B33: 46204 | C33: 577475 | D33: 102.9 | E33: 7523282 | F33: 5114815792 | G33: SEP | H33: ON | I33: EN | J33: Dental | K33: 210667685 | L33: 1000956326 | M33: =VLOOKUP(L33,Selma!H$1:H$3913,1,FALSE) -> 1000956326 | N33: In Selma's report | O33: Enrollee | P33: Self | Q33: Active Re-enrollee | R33: 27176 | S33: Kristopher | T33: Bayne | U33: 20.37 | V33: 78.88 | W33: 78.88 | X33: NULL | Y33: NULL | Z33: APTC_CSR | AA33: LOW | AB33: 83502GA002000801 | AC33: 3634 | AD33: Best Life Essential Basic Dental Plan | AE33: 83502 | AF33: BEST Life and Health Insurance Company | AG33: 51 | AH33: bayne2girls@gmail.com | AI33: 7705978010 | AJ33: 3 | AK33: GWINNETT | AL33: 30045 | AM33: AGENT | AN33: 1176094 | AO33: 1176094 | AP33: 18924885 | AQ33: Aslynn | AR33: Peacock | AS33: HealthSherpa | AT33: HealthSherpa | AU33: Enrolled | AV33: Enrolled | AW33: 46023 | AX33: 46387 | AY33: 45946 | AZ33: 45946 | BA33: 46020 | BB33: 46023 | BC33: 46387 | BD33: 45946 | BE33: 46020 | BF33: 45996 | BG33: 46002
A34: 2026 | B34: 46204 | C34: 577475 | D34: 102.9 | E34: 7523282 | F34: 5114815792 | G34: SEP | H34: ON | I34: EN | J34: Dental | K34: 210667685 | L34: 1000956323 | M34: =VLOOKUP(L34,Selma!H$1:H$3913,1,FALSE) -> 1000956323 | N34: In Selma's report | O34: Enrollee | P34: Child | Q34: Active Re-enrollee | R34: 38299 | S34: Mackenzie | T34: Bayne | U34: 19.07 | V34: 78.88 | W34: 78.88 | X34: NULL | Y34: NULL | Z34: APTC_CSR | AA34: LOW | AB34: 83502GA002000801 | AC34: 3634 | AD34: Best Life Essential Basic Dental Plan | AE34: 83502 | AF34: BEST Life and Health Insurance Company | AG34: 21 | AH34: bayne2girls@gmail.com | AI34: 7705978010 | AJ34: 3 | AK34: GWINNETT | AL34: 30045 | AM34: AGENT | AN34: 1176094 | AO34: 1176094 | AP34: 18924885 | AQ34: Aslynn | AR34: Peacock | AS34: HealthSherpa | AT34: HealthSherpa | AU34: Enrolled | AV34: Enrolled | AW34: 46023 | AX34: 46387 | AY34: 45946 | AZ34: 45946 | BA34: 46020 | BB34: 46023 | BC34: 46387 | BD34: 45946 | BE34: 46020 | BF34: 45996 | BG34: 46002
A35: 2026 | B35: 46204 | C35: 598880 | D35: 105.07 | E35: 9194141 | F35: 5127220391 | G35: SEP | H35: ON | I35: EN | J35: Dental | K35: 211603770 | L35: 1000992290 | M35: =VLOOKUP(L35,Selma!H$1:H$3913,1,FALSE) -> 1000992290 | N35: In Selma's report | O35: Enrollee | P35: Child | Q35: Active Re-enrollee | R35: 38106 | S35: Zacori | T35: Hurt | U35: 16.07 | V35: 33.24 | W35: 33.24 | X35: NULL | Y35: NULL | Z35: APTC_CSR | AA35: LOW | AB35: 83502GA002000801 | AC35: 3634 | AD35: Best Life Essential Basic Dental Plan | AE35: 83502 | AF35: BEST Life and Health Insurance Company | AG35: 21 | AH35: stephanie.hurt@ymail.com | AI35: 4042686997 | AJ35: 12 | AK35: Jones | AL35: 31032 | AM35: AGENT | AN35: 548849 | AO35: 548849 | AP35: 7658400 | AQ35: CHRISTINA FACAINE | AR35: BATTLE | AS35: HealthSherpa | AT35: HealthSherpa | AU35: Enrolled | AV35: Terminated | AW35: 46023 | AX35: 46387 | AY35: 46001 | AZ35: 45965 | BA35: 46161 | BB35: 46023 | BC35: 46173 | BD35: 45965 | BE35: 46161 | BF35: 46161 | BG35: 46161
A36: 2026 | B36: 46204 | C36: 598880 | D36: 105.07 | E36: 9194141 | F36: 5127220391 | G36: SEP | H36: ON | I36: EN | J36: Dental | K36: 211603770 | L36: 1000992291 | M36: =VLOOKUP(L36,Selma!H$1:H$3913,1,FALSE) -> 1000992291 | N36: In Selma's report | O36: Enrollee | P36: Child | Q36: Active Re-enrollee | R36: 39071 | S36: Zachary | T36: Hurt | U36: 16.07 | V36: 33.24 | W36: 33.24 | X36: NULL | Y36: NULL | Z36: APTC_CSR | AA36: LOW | AB36: 83502GA002000801 | AC36: 3634 | AD36: Best Life Essential Basic Dental Plan | AE36: 83502 | AF36: BEST Life and Health Insurance Company | AG36: 19 | AH36: stephanie.hurt@ymail.com | AI36: 4042686997 | AJ36: 12 | AK36: Jones | AL36: 31032 | AM36: AGENT | AN36: 548849 | AO36: 548849 | AP36: 7658400 | AQ36: CHRISTINA FACAINE | AR36: BATTLE | AS36: HealthSherpa | AT36: HealthSherpa | AU36: Enrolled | AV36: Enrolled | AW36: 46023 | AX36: 46387 | AY36: 46001 | AZ36: 45965 | BA36: 46161 | BB36: 46023 | BC36: 46387 | BD36: 45965 | BE36: 46161 | BF36: 46161 | BG36: 46161
A37: 2026 | B37: 46204 | C37: 625394 | D37: 100.81 | E37: 8751389 | F37: 5119263437 | G37: SEP | H37: ON | I37: EN | J37: Dental | K37: 211966421 | L37: 1001036214 | M37: =VLOOKUP(L37,Selma!H$1:H$3913,1,FALSE) -> 1001036214 | N37: In Selma's report | O37: Enrollee | P37: Child | Q37: Automatic Re-enrollee | R37: 40720 | S37: KHOI | T37: NGUYEN | U37: 27.65 | V37: 117.75 | W37: 117.75 | X37: NULL | Y37: NULL | Z37: APTC_CSR | AA37: LOW | AB37: 83502GA002000801 | AC37: 3634 | AD37: Best Life Essential Basic Dental Plan | AE37: 83502 | AF37: BEST Life and Health Insurance Company | AG37: 14 | AH37: nhattx3110888@uagins.org | AI37: 6262974622 | AJ37: 15 | AK37: DECATUR | AL37: 39817 | AM37: AGENT | AN37: 11052 | AO37: 11052 | AP37: 17142578 | AQ37: NGAN | AR37: JUNGBLUTH | AS37: HealthSherpa | AT37: HealthSherpa | AU37: Enrolled | AV37: Enrolled | AW37: 46023 | AX37: 46387 | AY37: 46019 | AZ37: 46003 | BA37: 46019 | BB37: 46023 | BC37: 46387 | BD37: 46003 | BE37: 46019 | BF37: 46097 | BG37: 46097
A38: 2026 | B38: 46204 | C38: 625394 | D38: 100.81 | E38: 8751389 | F38: 5119263437 | G38: SEP | H38: ON | I38: EN | J38: Dental | K38: 211966421 | L38: 1001036216 | M38: =VLOOKUP(L38,Selma!H$1:H$3913,1,FALSE) -> 1001036216 | N38: In Selma's report | O38: Enrollee | P38: Spouse | Q38: Automatic Re-enrollee | R38: 31389 | S38: OANH | T38: DANG | U38: 17.4 | V38: 117.75 | W38: 117.75 | X38: NULL | Y38: NULL | Z38: APTC_CSR | AA38: LOW | AB38: 83502GA002000801 | AC38: 3634 | AD38: Best Life Essential Basic Dental Plan | AE38: 83502 | AF38: BEST Life and Health Insurance Company | AG38: 40 | AH38: nhattx3110888@uagins.org | AI38: 6262974622 | AJ38: 15 | AK38: DECATUR | AL38: 39817 | AM38: AGENT | AN38: 11052 | AO38: 11052 | AP38: 17142578 | AQ38: NGAN | AR38: JUNGBLUTH | AS38: HealthSherpa | AT38: HealthSherpa | AU38: Enrolled | AV38: Enrolled | AW38: 46023 | AX38: 46387 | AY38: 46019 | AZ38: 46003 | BA38: 46019 | BB38: 46023 | BC38: 46387 | BD38: 46003 | BE38: 46019 | BF38: 46097 | BG38: 46097
A39: 2026 | B39: 46204 | C39: 625394 | D39: 100.81 | E39: 8751389 | F39: 5119263437 | G39: SEP | H39: ON | I39: EN | J39: Dental | K39: 211966421 | L39: 1001036215 | M39: =VLOOKUP(L39,Selma!H$1:H$3913,1,FALSE) -> 1001036215 | N39: In Selma's report | O39: Enrollee | P39: Child | Q39: Automatic Re-enrollee | R39: 42437 | S39: STEVEN | T39: NGUYEN | U39: 27.65 | V39: 117.75 | W39: 117.75 | X39: NULL | Y39: NULL | Z39: APTC_CSR | AA39: LOW | AB39: 83502GA002000801 | AC39: 3634 | AD39: Best Life Essential Basic Dental Plan | AE39: 83502 | AF39: BEST Life and Health Insurance Company | AG39: 9 | AH39: nhattx3110888@uagins.org | AI39: 6262974622 | AJ39: 15 | AK39: DECATUR | AL39: 39817 | AM39: AGENT | AN39: 11052 | AO39: 11052 | AP39: 17142578 | AQ39: NGAN | AR39: JUNGBLUTH | AS39: HealthSherpa | AT39: HealthSherpa | AU39: Enrolled | AV39: Enrolled | AW39: 46023 | AX39: 46387 | AY39: 46019 | AZ39: 46003 | BA39: 46019 | BB39: 46023 | BC39: 46387 | BD39: 46003 | BE39: 46019 | BF39: 46097 | BG39: 46097
... A49: 2026 | B49: 46204 | C49: 911633 | D49: 111.98 | E49: 6183470 | F49: 5148764469 | G49: OE | H49: CN | I49: EN | J49: Dental | K49: 210959356 | L49: 1001510407 | M49: =VLOOKUP(L49,Selma!H$1:H$3913,1,FALSE) -> 1001510407 | N49: In Selma's report | O49: Enrollee | P49: Child | Q49: Automatic Re-enrollee | R49: 39555 | S49: Aniyah | T49: Sims | U49: 33.34 | V49: 106.45 | W49: 106.45 | X49: NULL | Y49: NULL | Z49: APTC_CSR | AA49: LOW | AB49: 83502GA002000801 | AC49: 3634 | AD49: Best Life Essential Basic Dental Plan | AE49: 83502 | AF49: BEST Life and Health Insurance Company | AG49: 17 | AH49: aaron7918@gmail.com | AI49: 9174124470 | AJ49: 3 | AK49: DOUGLAS | AL49: 30135 | AM49: AGENT | AN49: 6168 | AO49: 6168 | AP49: 17128585 | AQ49: JUSTIN | AR49: FITZGERALD | AS49: NULL | AT49: NULL | AU49: Cancelled | AV49: Cancelled | AW49: 46023 | AX49: 46023 | AY49: 45946 | AZ49: 45946 | BA49: 46005 | BB49: 46023 | BC49: 46023 | BD49: 45946 | BE49: 46005 | BF49: 45934 | BG49: 46005
A50: 2026 | B50: 46204 | C50: 915097 | D50: 112.57 | E50: 8873685 | F50: 5138267025 | G50: QEP | H50: ON | I50: EN | J50: Dental | K50: 1000159512 | L50: 1001515532 | M50: =VLOOKUP(L50,Selma!H$1:H$3913,1,FALSE) -> 1001515532 | N50: In Selma's report | O50: Enrollee | P50: Spouse | Q50: Active Re-enrollee | R50: 27201 | S50: ASMA | T50: HAMEED | U50: 20.37 | V50: 40.74 | W50: 40.74 | X50: 0 | Y50: NULL | Z50: APTC_CSR | AA50: LOW | AB50: 83502GA002000801 | AC50: 3634 | AD50: Best Life Essential Basic Dental Plan | AE50: 83502 | AF50: BEST Life and Health Insurance Company | AG50: 51 | AH50: jmemon@yahoo.com | AI50: 6787949158 | AJ50: 3 | AK50: Gwinnett | AL50: 30043 | AM50: AGENT | AN50: 553250 | AO50: 553250 | AP50: 7082023 | AQ50: NIZAR NOORALI | AR50: JANMOHAMMAD | AS50: HealthSherpa | AT50: HealthSherpa | AU50: Enrolled | AV50: Enrolled | AW50: 46143 | AX50: 46387 | AY50: 46177 | AZ50: 46122 | BA50: 46177 | BB50: 46143 | BC50: 46387 | BD50: 46122 | BE50: 46177 | BF50: 46113 | BG50: 46146
A51: 2026 | B51: 46204 | C51: 930553 | D51: 124.55 | E51: 5926128 | F51: 5136906593 | G51: OE | H51: CN | I51: EN | J51: Dental | K51: 211373616 | L51: 1001541995 | M51: =VLOOKUP(L51,Selma!H$1:H$3913,1,FALSE) -> #N/A | N51: Not in Selma's report | O51: Enrollee | P51: Child | Q51: Automatic Re-enrollee | R51: 41974 | S51: Joseph | T51: Crew | U51: 36.54 | V51: 76.33 | W51: 76.33 | X51: NULL | Y51: NULL | Z51: APTC_CSR | AA51: HIGH | AB51: 83502GA002000301 | AC51: 3631 | AD51: Best Life Superior Dental Plan | AE51: 83502 | AF51: BEST Life and Health Insurance Company | AG51: 11 | AH51: mirkacrew@gmail.com | AI51: 2293218886 | AJ51: 8 | AK51: WEBSTER | AL51: 31825 | AM51: AGENT | AN51: 550979 | AO51: 550979 | AP51: 16097917 | AQ51: OSAMA | AR51: ESTWANI | AS51: NULL | AT51: NULL | AU51: Enrolled | AV51: Enrolled | AW51: 46023 | AX51: 46387 | AY51: 45947 | AZ51: 45947 | BA51: 45947 | BB51: 46023 | BC51: 46387 | BD51: 45947 | BE51: 45947 | BF51: 45934 | BG51: 46006
A52: 2026 | B52: 46204 | C52: 965695 | D52: 102.64 | E52: 7789541 | F52: 5134279928 | G52: OE | H52: EDE | I52: EN | J52: Dental | K52: 211698911 | L52: 1001600480 | M52: =VLOOKUP(L52,Selma!H$1:H$3913,1,FALSE) -> 1001600480 | N52: In Selma's report | O52: Enrollee | P52: Spouse | Q52: Active Re-enrollee | R52: 25462 | S52: Fredrick | T52: Seagle | U52: 20.37 | V52: 40.74 | W52: 40.74 | X52: 0 | Y52: NULL | Z52: APTC_CSR | AA52: LOW | AB52: 83502GA002000801 | AC52: 3634 | AD52: Best Life Essential Basic Dental Plan | AE52: 83502 | AF52: BEST Life and Health Insurance Company | AG52: 56 | AH52: rickseagle@gmail.com | AI52: 4049882030 | AJ52: 3 | AK52: Forsyth | AL52: 30024 | AM52: AGENT | AN52: 2110 | AO52: 2110 | AP52: 20185923 | AQ52: CARRIE | AR52: LIN | AS52: HealthSherpa | AT52: HealthSherpa | AU52: Enrolled | AV52: Enrolled | AW52: 46023 | AX52: 46387 | AY52: 45996 | AZ52: 45977 | BA52: 46006 | BB52: 46023 | BC52: 46387 | BD52: 45977 | BE52: 46006 | BF52: 46006 | BG52: 46006
A53: 2026 | B53: 46204 | C53: 965695 | D53: 102.64 | E53: 7789541 | F53: 5134279928 | G53: OE | H53: EDE | I53: EN | J53: Dental | K53: 210713882 | L53: 1001600480 | M53: =VLOOKUP(L53,Selma!H$1:H$3913,1,FALSE) -> 1001600480 | N53: In Selma's report | O53: Enrollee | P53: Spouse | Q53: Active Re-enrollee | R53: 25462 | S53: Fredrick | T53: Seagle | U53: 25.77 | V53: 51.54 | W53: 51.54 | X53: NULL | Y53: NULL | Z53: APTC_CSR | AA53: LOW | AB53: 83502GA002000601 | AC53: 3632 | AD53: Best Life Essential Value Dental Plan | AE53: 83502 | AF53: BEST Life and Health Insurance Company | AG53: 56 | AH53: rickseagle@gmail.com | AI53: 4049882030 | AJ53: 3 | AK53: Forsyth | AL53: 30024 | AM53: AGENT | AN53: 2110 | AO53: 2110 | AP53: 20185923 | AQ53: CARRIE | AR53: LIN | AS53: HealthSherpa | AT53: HealthSherpa | AU53: Cancelled | AV53: Cancelled | AW53: 46023 | AX53: 46023 | AY53: 45946 | AZ53: 45946 | BA53: 46006 | BB53: 46023 | BC53: 46023 | BD53: 45946 | BE53: 46006 | BF53: 46006 | BG53: 46006
A54: 2026 | B54: 46204 | C54: 935244 | D54: NULL | E54: 7888840 | F54: NULL | G54: OE | H54: ON | I54: EN | J54: Dental | K54: 212101195 | L54: 1002440550 | M54: =VLOOKUP(L54,Selma!H$1:H$3913,1,FALSE) -> 1002440550 | N54: In Selma's report | O54: Subscriber | P54: Self | Q54: New Consumer | R54: 30638 | S54: Holly | T54: Chaney | U54: 33.78 | V54: 71.65 | W54: 71.65 | X54: NULL | Y54: NULL | Z54: QHP | AA54: HIGH | AB54: 83502GA002000701 | AC54: 3633 | AD54: Best Life Preferred Dental Plan | AE54: 83502 | AF54: BEST Life and Health Insurance Company | AG54: 42 | AH54: holly@cssbrokers.com | AI54: 7708536510 | AJ54: 13 | AK54: Chattooga | AL54: 30753 | AM54: NULL | AN54: NULL | AO54: NULL | AP54: NULL | AQ54: NULL | AR54: NULL | AS54: NULL | AT54: NULL | AU54: Cancelled | AV54: Cancelled | AW54: 46054 | AX54: 46054 | AY54: NULL | AZ54: 46014 | BA54: 46094 | BB54: 46054 | BC54: 46054 | BD54: 46014 | BE54: 46094 | BF54: 46014 | BG54: 46094
A55: 2026 | B55: 46204 | C55: 989585 | D55: 102.35 | E55: 6981713 | F55: 5157648070 | G55: SEP | H55: ON | I55: EN | J55: Dental | K55: 211175021 | L55: 1001640096 | M55: =VLOOKUP(L55,Selma!H$1:H$3913,1,FALSE) -> 1001640096 | N55: In Selma's report | O55: Enrollee | P55: Spouse | Q55: Active Re-enrollee | R55: 24871 | S55: pamela | T55: bethea | U55: 25.77 | V55: 51.54 | W55: 51.54 | X55: NULL | Y55: NULL | Z55: APTC_CSR | AA55: LOW | AB55: 83502GA002000601 | AC55: 3632 | AD55: Best Life Essential Value Dental Plan | AE55: 83502 | AF55: BEST Life and Health Insurance Company | AG55: 57 | AH55: norman@serenityhouseatl.org | AI55: 6782314002 | AJ55: 3 | AK55: DEKALB | AL55: 30058 | AM55: AGENT | AN55: 867987 | AO55: 867987 | AP55: 9288416 | AQ55: LIZETH | AR55: GARCIA | AS55: NULL | AT55: NULL | AU55: Enrolled | AV55: Enrolled | AW55: 46023 | AX55: 46387 | AY55: 45946 | AZ55: 45946 | BA55: 45973 | BB55: 46023 | BC55: 46387 | BD55: 45946 | BE55: 45973 | BF55: 45973 | BG55: 45973
A56: 2026 | B56: 46204 | C56: 1166772 | D56: 118.2 | E56: 8132214 | F56: NULL | G56: OE | H56: EDE | I56: EN | J56: Dental | K56: 212188074 | L56: 1006501517 | M56: =VLOOKUP(L56,Selma!H$1:H$3913,1,FALSE) -> #N/A | N56: Not in Selma's report | O56: Enrollee | P56: Child | Q56: New Consumer | R56: 38798 | S56: Stanley | T56: Goodman | U56: 19.07 | V56: 39.44 | W56: 39.44 | X56: 0 | Y56: NULL | Z56: APTC_CSR | AA56: LOW | AB56: 83502GA002000801 | AC56: 3634 | AD56: Best Life Essential Basic Dental Plan | AE56: 83502 | AF56: BEST Life and Health Insurance Company | AG56: 19 | AH56: clendeningamber@gmail.com | AI56: 4042474300 | AJ56: 3 | AK56: Clayton | AL56: 30236 | AM56: AGENT | AN56: 551050 | AO56: 551050 | AP56: 20356380 | AQ56: Rodrigo | AR56: da Silva | AS56: HealthSherpa | AT56: HealthSherpa | AU56: Cancelled | AV56: Cancelled | AW56: 46054 | AX56: 46054 | AY56: NULL | AZ56: 46034 | BA56: 46094 | BB56: 46054 | BC56: 46054 | BD56: 46034 | BE56: 46094 | BF56: 46034 | BG56: 46094
A57: 2026 | B57: 46204 | C57: 1208978 | D57: 122.93 | E57: 7904136 | F57: GAT6253932990 | G57: SEP | H57: RR | I57: EN | J57: Dental | K57: 211429411 | L57: 1002220915 | M57: =VLOOKUP(L57,Selma!H$1:H$3913,1,FALSE) -> 1002220915 | N57: In Selma's report | O57: Enrollee | P57: Child | Q57: Active Re-enrollee | R57: 44886 | S57: XIOMARA | T57: TRICHE | U57: 41.11 | V57: 85.88 | W57: 85.88 | X57: NULL | Y57: NULL | Z57: APTC_CSR | AA57: HIGH | AB57: 83502GA002000301 | AC57: 3631 | AD57: Best Life Superior Dental Plan | AE57: 83502 | AF57: BEST Life and Health Insurance Company | AG57: 3 | AH57: anais.warren@gmail.com | AI57: 6787207510 | AJ57: 3 | AK57: FULTON | AL57: 30349 | AM57: AGENT | AN57: 1023059 | AO57: 1023059 | AP57: 7639809 | AQ57: Carl | AR57: Jackson | AS57: HealthSherpa | AT57: HealthSherpa | AU57: Cancelled | AV57: Cancelled | AW57: 46023 | AX57: 46023 | AY57: 45947 | AZ57: 45947 | BA57: 46016 | BB57: 46023 | BC57: 46023 | BD57: 45947 | BE57: 46016 | BF57: 46016 | BG57: 46016
A58: 2026 | B58: 46204 | C58: 1577769 | D58: 101.31 | E58: 8078999 | F58: NULL | G58: SEP | H58: RR | I58: EN | J58: Dental | K58: 211420883 | L58: 1003771032 | M58: =VLOOKUP(L58,Selma!H$1:H$3913,1,FALSE) -> 1003771032 | N58: In Selma's report | O58: Enrollee | P58: Child | Q58: Active Re-enrollee | R58: 40428 | S58: Siena | T58: Lockridge | U58: 29.04 | V58: 46.78 | W58: 17.74 | X58: 29.04 | Y58: NULL | Z58: APTC_CSR | AA58: LOW | AB58: 83502GA002000801 | AC58: 3634 | AD58: Best Life Essential Basic Dental Plan | AE58: 83502 | AF58: BEST Life and Health Insurance Company | AG58: 15 | AH58: jeanking@yahoo.com | AI58: NULL | AJ58: 2 | AK58: NULL | AL58: 30650 | AM58: AGENT | AN58: 6039 | AO58: 6039 | AP58: 19556249 | AQ58: JOSUN | AR58: STRAATSMA | AS58: HealthSherpa | AT58: HealthSherpa | AU58: Enrolled | AV58: Enrolled | AW58: 46023 | AX58: 46387 | AY58: 45947 | AZ58: 45947 | BA58: 46085 | BB58: 46023 | BC58: 46387 | BD58: 45947 | BE58: 46085 | BF58: 46029 | BG58: 46029
A59: 2026 | B59: 46204 | C59: 1783569 | D59: 100.26 | E59: 8080953 | F59: NULL | G59: SEP | H59: ON | I59: EN | J59: Dental | K59: 212074536 | L59: 1006689984 | M59: =VLOOKUP(L59,Selma!H$1:H$3913,1,FALSE) -> #N/A | N59: Not in Selma's report | O59: Enrollee | P59: Child | Q59: New Consumer | R59: 40834 | S59: Mariano | T59: Deluna | U59: 35.11 | V59: 66.43 | W59: 66.43 | X59: NULL | Y59: NULL | Z59: APTC_CSR | AA59: HIGH | AB59: 83502GA002000701 | AC59: 3633 | AD59: Best Life Preferred Dental Plan | AE59: 83502 | AF59: BEST Life and Health Insurance Company | AG59: 14 | AH59: carlosdeluna18@icloud.com | AI59: 2293454438 | AJ59: 15 | AK59: Irwin | AL59: 31774 | AM59: AGENT | AN59: 1337096 | AO59: 1337096 | AP59: 21459398 | AQ59: Larissa | AR59: Nesmejanova | AS59: MyMFG | AT59: MyMFG | AU59: Enrolled | AV59: Enrolled | AW59: 46054 | AX59: 46387 | AY59: 46033 | AZ59: 46008 | BA59: 46033 | BB59: 46054 | BC59: 46387 | BD59: 46029 | BE59: 46033 | BF59: 46029 | BG59: 46029
A60: 2026 | B60: 46204 | C60: 1913482 | D60: 112.57 | E60: 8997920 | F60: NULL | G60: QEP | H60: ON | I60: EN | J60: Dental | K60: 1000180472 | L60: 1007695776 | M60: =VLOOKUP(L60,Selma!H$1:H$3913,1,FALSE) -> 1007695776 | N60: In Selma's report | O60: Enrollee | P60: Child | Q60: New Consumer | R60: 38955 | S60: Lohan | T60: Howard | U60: 24.12 | V60: 82.26 | W60: 82.26 | X60: 0 | Y60: NULL | Z60: APTC_CSR | AA60: LOW | AB60: 83502GA002000601 | AC60: 3632 | AD60: Best Life Essential Value Dental Plan | AE60: 83502 | AF60: BEST Life and Health Insurance Company | AG60: 19 | AH60: pizzaisking@gmail.com | AI60: 4044573143 | AJ60: 3 | AK60: Fulton | AL60: 30306 | AM60: AGENT | AN60: 550332 | AO60: 550332 | AP60: 11886143 | AQ60: GENE | AR60: BOROK | AS60: NULL | AT60: NULL | AU60: Enrolled | AV60: Enrolled | AW60: 46143 | AX60: 46387 | AY60: 46138 | AZ60: 46134 | BA60: 46138 | BB60: 46143 | BC60: 46387 | BD60: 46134 | BE60: 46138 | BF60: 46134 | BG60: 46134
A61: 2026 | B61: 46204 | C61: 1913482 | D61: 112.57 | E61: 8997920 | F61: NULL | G61: QEP | H61: ON | I61: EN | J61: Dental | K61: 1000180472 | L61: 1007695777 | M61: =VLOOKUP(L61,Selma!H$1:H$3913,1,FALSE) -> 1007695777 | N61: In Selma's report | O61: Enrollee | P61: Child | Q61: New Consumer | R61: 42467 | S61: Riley | T61: Howard | U61: 32.37 | V61: 82.26 | W61: 82.26 | X61: 0 | Y61: NULL | Z61: APTC_CSR | AA61: LOW | AB61: 83502GA002000601 | AC61: 3632 | AD61: Best Life Essential Value Dental Plan | AE61: 83502 | AF61: BEST Life and Health Insurance Company | AG61: 10 | AH61: pizzaisking@gmail.com | AI61: 4044573143 | AJ61: 3 | AK61: Fulton | AL61: 30306 | AM61: AGENT | AN61: 550332 | AO61: 550332 | AP61: 11886143 | AQ61: GENE | AR61: BOROK | AS61: NULL | AT61: NULL | AU61: Enrolled | AV61: Enrolled | AW61: 46143 | AX61: 46387 | AY61: 46138 | AZ61: 46134 | BA61: 46138 | BB61: 46143 | BC61: 46387 | BD61: 46134 | BE61: 46138 | BF61: 46134 | BG61: 46134
A62: 2026 | B62: 46204 | C62: 2320908 | D62: 105.07 | E62: 9109655 | F62: NULL | G62: QEP | H62: EDE | I62: EN | J62: Dental | K62: 212230463 | L62: 1006979969 | M62: =VLOOKUP(L62,Selma!H$1:H$3913,1,FALSE) -> #N/A | N62: Not in Selma's report | O62: Enrollee | P62: Child | Q62: New Consumer | R62: 38346 | S62: Muhammad | T62: Shahzad | U62: 35.79 | V62: 71.58 | W62: 71.58 | X62: 0 | Y62: NULL | Z62: APTC_CSR | AA62: HIGH | AB62: 83502GA002000301 | AC62: 3631 | AD62: Best Life Superior Dental Plan | AE62: 83502 | AF62: BEST Life and Health Insurance Company | AG62: 21 | AH62: waizmuhammad367@gmail.com | AI62: 2294396880 | AJ62: 1 | AK62: Lee | AL62: 31763 | AM62: AGENT | AN62: 2847 | AO62: 2847 | AP62: 17748414 | AQ62: DANIELLE | AR62: NOACK | AS62: HealthSherpa | AT62: HealthSherpa | AU62: Cancelled | AV62: Cancelled | AW62: 46054 | AX62: 46054 | AY62: NULL | AZ62: 46037 | BA62: 46051 | BB62: 46054 | BC62: 46054 | BD62: 46041 | BE62: 46051 | BF62: 46153 | BG62: 46153
A63: 2026 | B63: 46204 | C63: 1823 | D63: 118.2 | E63: 9014736 | F63: 5460619672 | G63: SEP | H63: ON | I63: EN | J63: Dental | K63: 212119392 | L63: 1000003015 | M63: =VLOOKUP(L63,Selma!H$1:H$3913,1,FALSE) -> 1000003015 | N63: In Selma's report | O63: Subscriber | P63: Self | Q63: New Consumer | R63: 30757 | S63: Robert | T63: Royster | U63: 31.94 | V63: 31.94 | W63: 31.94 | X63: NULL | Y63: NULL | Z63: APTC_CSR | AA63: HIGH | AB63: 83502GA002000701 | AC63: 3633 | AD63: Best Life Preferred Dental Plan | AE63: 83502 | AF63: BEST Life and Health Insurance Company | AG63: 41 | AH63: rcroyster09@gmail.com | AI63: 7703077557 | AJ63: 2 | AK63: Barrow | AL63: 30680 | AM63: AGENT | AN63: 1469317 | AO63: 1469317 | AP63: 21344380 | AQ63: Charles | AR63: Kaetzel | AS63: HealthSherpa | AT63: HealthSherpa | AU63: Terminated | AV63: Terminated | AW63: 46054 | AX63: 46112 | AY63: 46029 | AZ63: 46020 | BA63: 46154 | BB63: 46054 | BC63: 46112 | BD63: 46020 | BE63: 46154 | BF63: 46136 | BG63: 46136
A64: 2026 | B64: 46204 | C64: 3300 | D64: 100.8 | E64: 8657599 | F64: GAT111797041 | G64: SEP | H64: ON | I64: EN | J64: Dental | K64: 212178571 | L64: 1000005486 | M64: =VLOOKUP(L64,Selma!H$1:H$3913,1,FALSE) -> 1000005486 | N64: In Selma's report | O64: Subscriber | P64: Child | Q64: New Consumer | R64: 39062 | S64: ASHLEE | T64: FISHER | U64: 16.07 | V64: 16.07 | W64: 16.07 | X64: NULL | Y64: NULL | Z64: APTC_CSR | AA64: LOW | AB64: 83502GA002000801 | AC64: 3634 | AD64: Best Life Essential Basic Dental Plan | AE64: 83502 | AF64: BEST Life and Health Insurance Company | AG64: 19 | AH64: beccafisher09@gmail.com | AI64: 4783602590 | AJ64: 12 | AK64: Bibb | AL64: 31204 | AM64: AGENT | AN64: 2828 | AO64: 2828 | AP64: 9233271 | AQ64: daniel | AR64: yoon | AS64: HealthSherpa | AT64: HealthSherpa | AU64: Enrolled | AV64: Enrolled | AW64: 46054 | AX64: 46387 | AY64: 46054 | AZ64: 46031 | BA64: 46083 | BB64: 46054 | BC64: 46387 | BD64: 46031 | BE64: 46083 | BF64: 46085 | BG64: 46115
A65: 2026 | B65: 46204 | C65: 9315 | D65: 107.35 | E65: 8090698 | F65: 5167582958 | G65: SEP | H65: ON | I65: EN | J65: Dental | K65: 210704775 | L65: 1000015424 | M65: =VLOOKUP(L65,Selma!H$1:H$3913,1,FALSE) -> 1000015424 | N65: In Selma's report | O65: Subscriber | P65: Self | Q65: Automatic Re-enrollee | R65: 26147 | S65: Cheryl | T65: Bell | U65: 38.61 | V65: 38.61 | W65: 38.61 | X65: NULL | Y65: NULL | Z65: APTC_CSR | AA65: HIGH | AB65: 83502GA002000301 | AC65: 3631 | AD65: Best Life Superior Dental Plan | AE65: 83502 | AF65: BEST Life and Health Insurance Company | AG65: 54 | AH65: cbh0508@bellsouth.net | AI65: 7068316958 | AJ65: 5 | AK65: BURKE | AL65: 30456 | AM65: AGENT | AN65: 6921 | AO65: 6921 | AP65: 20842475 | AQ65: LEYA | AR65: BELACHEW | AS65: NULL | AT65: NULL | AU65: Enrolled | AV65: Enrolled | AW65: 46023 | AX65: 46387 | AY65: 45946 | AZ65: 45946 | BA65: 46037 | BB65: 46023 | BC65: 46387 | BD65: 45946 | BE65: 46037 | BF65: 46029 | BG65: 46037
A66: 2026 | B66: 46204 | C66: 48948 | D66: 108.88 | E66: 8533911 | F66: 5144901047 | G66: SEP | H66: ON | I66: EN | J66: Dental | K66: 211590584 | L66: 1000081035 | M66: =VLOOKUP(L66,Selma!H$1:H$3913,1,FALSE) -> 1000081035 | N66: In Selma's report | O66: Subscriber | P66: Child | Q66: New Consumer | R66: 45104 | S66: Henry | T66: Vo | U66: 36.54 | V66: 36.54 | W66: 36.54 | X66: 0 | Y66: NULL | Z66: APTC_CSR | AA66: HIGH | AB66: 83502GA002000701 | AC66: 3633 | AD66: Best Life Preferred Dental Plan | AE66: 83502 | AF66: BEST Life and Health Insurance Company | AG66: 2 | AH66: trinhmai1403@gmail.com | AI66: 6787790888 | AJ66: 8 | AK66: MUSCOGEE | AL66: 31904 | AM66: AGENT | AN66: 547691 | AO66: 547691 | AP66: 441704 | AQ66: ALICIA THUY | AR66: CHAU | AS66: NULL | AT66: NULL | AU66: Cancelled | AV66: Cancelled | AW66: 46023 | AX66: 46023 | AY66: NULL | AZ66: 45964 | BA66: 46065 | BB66: 46023 | BC66: 46023 | BD66: 45964 | BE66: 46065 | BF66: 46070 | BG66: 46070
A67: 2026 | B67: 46204 | C67: 61952 | D67: 100.06 | E67: 8818351 | F67: 5136265888 | G67: SEP | H67: ON | I67: EN | J67: Dental | K67: 211274314 | L67: 1000102609 | M67: =VLOOKUP(L67,Selma!H$1:H$3913,1,FALSE) -> 1000102609 | N67: In Selma's report | O67: Subscriber | P67: Self | Q67: Active Re-enrollee | R67: 35105 | S67: Lushik | T67: Wahba | U67: 44.77 | V67: 44.77 | W67: 44.77 | X67: NULL | Y67: NULL | Z67: APTC_CSR | AA67: HIGH | AB67: 83502GA002000301 | AC67: 3631 | AD67: Best Life Superior Dental Plan | AE67: 83502 | AF67: BEST Life and Health Insurance Company | AG67: 29 | AH67: lushikwahba@bennington.edu | AI67: 8028297341 | AJ67: 3 | AK67: Fulton | AL67: 30310 | AM67: AGENT | AN67: 8070 | AO67: 8070 | AP67: 17555101 | AQ67: MERLE | AR67: CRIM-DUBOIS | AS67: NULL | AT67: NULL | AU67: Terminated | AV67: Terminated | AW67: 46023 | AX67: 46081 | AY67: 45946 | AZ67: 45946 | BA67: 46124 | BB67: 46023 | BC67: 46081 | BD67: 45946 | BE67: 46124 | BF67: 46106 | BG67: 46106
A68: 2026 | B68: 46204 | C68: 64194 | D68: 115.02 | E68: 5930509 | F68: 5156584275 | G68: OE | H68: CN | I68: EN | J68: Dental | K68: 211899780 | L68: 1000106277 | M68: =VLOOKUP(L68,Selma!H$1:H$3913,1,FALSE) -> #N/A | N68: Not in Selma's report | O68: Subscriber | P68: Self | Q68: Active Re-enrollee | R68: 24628 | S68: Rekha | T68: Sutradhar | U68: 44.77 | V68: 44.77 | W68: 44.77 | X68: NULL | Y68: NULL | Z68: APTC_CSR | AA68: HIGH | AB68: 83502GA002000301 | AC68: 3631 | AD68: Best Life Superior Dental Plan | AE68: 83502 | AF68: BEST Life and Health Insurance Company | AG68: 58 | AH68: rrsutradhar@gmail.com | AI68: 6786505010 | AJ68: 3 | AK68: Gwinnett | AL68: 30078 | AM68: AGENT | AN68: 550984 | AO68: 550984 | AP68: 7037754 | AQ68: IMTIAZ HANNAN | AR68: CHOUDHURY | AS68: HealthSherpa | AT68: HealthSherpa | AU68: Cancelled | AV68: Cancelled | AW68: 46023 | AX68: 46023 | AY68: NULL | AZ68: 45999 | BA68: 46017 | BB68: 46023 | BC68: 46023 | BD68: 45999 | BE68: 46017 | BF68: 45934 | BG68: 46020
A69: 2026 | B69: 46204 | C69: 76379 | D69: 113.48 | E69: 6286343 | F69: GAT130072144 | G69: OE | H69: CN | I69: EN | J69: Dental | K69: 211655805 | L69: 1000126392 | M69: =VLOOKUP(L69,Selma!H$1:H$3913,1,FALSE) -> 1000126392 | N69: In Selma's report | O69: Subscriber | P69: Self | Q69: Automatic Re-enrollee | R69: 27001 | S69: DERRICK | T69: MOBLEY | U69: 36.67 | V69: 36.67 | W69: 36.67 | X69: 0 | Y69: NULL | Z69: APTC_CSR | AA69: HIGH | AB69: 83502GA002000701 | AC69: 3633 | AD69: Best Life Preferred Dental Plan | AE69: 83502 | AF69: BEST Life and Health Insurance Company | AG69: 52 | AH69: mobley_derrick@yahoo.com | AI69: 6788652046 | AJ69: 3 | AK69: Fulton | AL69: 30213 | AM69: AGENT | AN69: 554175 | AO69: 554175 | AP69: 11170582 | AQ69: NIQUIA SHANTAE | AR69: BENFORD | AS69: HealthSherpa | AT69: HealthSherpa | AU69: Terminated | AV69: Terminated | AW69: 46023 | AX69: 46142 | AY69: 46039 | AZ69: 45972 | BA69: 46186 | BB69: 46023 | BC69: 46142 | BD69: 45972 | BE69: 46186 | BF69: 45934 | BG69: 45972
A70: 2026 | B70: 46204 | C70: 77661 | D70: 103.83 | E70: 6127476 | F70: 5125490462 | G70: OE | H70: CN | I70: EN | J70: Dental | K70: 211979667 | L70: 1000128551 | M70: =VLOOKUP(L70,Selma!H$1:H$3913,1,FALSE) -> 1000128551 | N70: In Selma's report | O70: Subscriber | P70: Self | Q70: Active Re-enrollee | R70: 32697 | S70: Emily | T70: Smith | U70: 44.77 | V70: 44.77 | W70: 44.77 | X70: 0 | Y70: NULL | Z70: APTC_CSR | AA70: HIGH | AB70: 83502GA002000301 | AC70: 3631 | AD70: Best Life Superior Dental Plan | AE70: 83502 | AF70: BEST Life and Health Insurance Company | AG70: 36 | AH70: emilyt.smith89@gmail.com | AI70: 4047503505 | AJ70: 3 | AK70: Henry | AL70: 30281 | AM70: AGENT | AN70: 867178 | AO70: 867178 | AP70: 19099396 | AQ70: Joshua | AR70: Richstone | AS70: JET Health Solutions | AT70: JET Health | AU70: Enrolled | AV70: Enrolled | AW70: 46023 | AX70: 46387 | AY70: 46029 | AZ70: 46003 | BA70: 46029 | BB70: 46023 | BC70: 46387 | BD70: 46003 | BE70: 46029 | BF70: 45934 | BG70: 46003
A71: 2026 | B71: 46204 | C71: 117247 | D71: 101.98 | E71: 9320174 | F71: GAT3677418714 | G71: QEP | H71: ON | I71: EN | J71: Dental | K71: 1000265460 | L71: 1000194163 | M71: =VLOOKUP(L71,Selma!H$1:H$3913,1,FALSE) -> 1000194163 | N71: In Selma's report | O71: Subscriber | P71: Self | Q71: Active Re-enrollee | R71: 27585 | S71: TONIKA | T71: TCHAMPO | U71: 20.37 | V71: 20.37 | W71: 20.37 | X71: 0 | Y71: NULL | Z71: APTC_CSR | AA71: LOW | AB71: 83502GA002000801 | AC71: 3634 | AD71: Best Life Essential Basic Dental Plan | AE71: 83502 | AF71: BEST Life and Health Insurance Company | AG71: 50 | AH71: t_tchampo@yahoo.com | AI71: 2052760615 | AJ71: 3 | AK71: Fulton | AL71: 30213 | AM71: AGENT | AN71: 972695 | AO71: 972695 | AP71: 20827901 | AQ71: Salihaa | AR71: Hall | AS71: NULL | AT71: NULL | AU71: Pending | AV71: Pending | AW71: 46204 | AX71: 46387 | AY71: NULL | AZ71: 46183 | BA71: 46183 | BB71: 46204 | BC71: 46387 | BD71: 46183 | BE71: 46183 | BF71: 46183 | BG71: 46183
A72: 2026 | B72: 46204 | C72: 117247 | D72: 101.98 | E72: 9320174 | F72: GAT3677418714 | G72: QEP | H72: ON | I72: EN | J72: Dental | K72: 211996342 | L72: 1000194163 | M72: =VLOOKUP(L72,Selma!H$1:H$3913,1,FALSE) -> 1000194163 | N72: In Selma's report | O72: Subscriber | P72: Self | Q72: Active Re-enrollee | R72: 27585 | S72: Tonika | T72: Tchampo | U72: 20.37 | V72: 20.37 | W72: 20.37 | X72: NULL | Y72: NULL | Z72: APTC_CSR | AA72: LOW | AB72: 83502GA002000801 | AC72: 3634 | AD72: Best Life Essential Basic Dental Plan | AE72: 83502 | AF72: BEST Life and Health Insurance Company | AG72: 50 | AH72: t_tchampo@yahoo.com | AI72: 2052760615 | AJ72: 3 | AK72: Fulton | AL72: 30213 | AM72: AGENT | AN72: 972695 | AO72: 972695 | AP72: 20827901 | AQ72: Salihaa | AR72: Hall | AS72: NULL | AT72: NULL | AU72: Cancelled | AV72: Cancelled | AW72: 46023 | AX72: 46023 | AY72: NULL | AZ72: 46005 | BA72: 46183 | BB72: 46023 | BC72: 46023 | BD72: 46005 | BE72: 46183 | BF72: 46183 | BG72: 46183
A73: 2026 | B73: 46204 | C73: 140259 | D73: 119.62 | E73: 8098292 | F73: 5426159243 | G73: OE | H73: ON | I73: EN | J73: Dental | K73: 212172418 | L73: 1000232235 | M73: =VLOOKUP(L73,Selma!H$1:H$3913,1,FALSE) -> 1000232235 | N73: In Selma's report | O73: Subscriber | P73: Self | Q73: New Consumer | R73: 35343 | S73: Marvis | T73: Thomas | U73: 44.77 | V73: 44.77 | W73: 44.77 | X73: 0 | Y73: NULL | Z73: APTC_CSR | AA73: HIGH | AB73: 83502GA002000301 | AC73: 3631 | AD73: Best Life Superior Dental Plan | AE73: 83502 | AF73: BEST Life and Health Insurance Company | AG73: 29 | AH73: marvis.thomas150@gmail.com | AI73: 6785233124 | AJ73: 3 | AK73: Fulton | AL73: 30331 | AM73: AGENT | AN73: 551223 | AO73: 551223 | AP73: 19890916 | AQ73: JACKELINE | AR73: PEREZ | AS73: HealthSherpa | AT73: HealthSherpa | AU73: Cancelled | AV73: Cancelled | AW73: 46054 | AX73: 46054 | AY73: NULL | AZ73: 46030 | BA73: 46191 | BB73: 46054 | BC73: 46054 | BD73: 46030 | BE73: 46191 | BF73: 46030 | BG73: 46191
A74: 2026 | B74: 46204 | C74: 161678 | D74: 102.24 | E74: 5753070 | F74: 5144182251 | G74: OE | H74: CN | I74: EN | J74: Dental | K74: 211330507 | L74: 1000267642 | M74: =VLOOKUP(L74,Selma!H$1:H$3913,1,FALSE) -> 1000267642 | N74: In Selma's report | O74: Subscriber | P74: Self | Q74: Automatic Re-enrollee | R74: 34596 | S74: DENARD | T74: ANGLIN | U74: 25.77 | V74: 25.77 | W74: 25.77 | X74: NULL | Y74: NULL | Z74: APTC_CSR | AA74: LOW | AB74: 83502GA002000601 | AC74: 3632 | AD74: Best Life Essential Value Dental Plan | AE74: 83502 | AF74: BEST Life and Health Insurance Company | AG74: 31 | AH74: danglin.rws@gmail.com | AI74: 7704026525 | AJ74: 3 | AK74: NEWTON | AL74: 30014 | AM74: AGENT | AN74: 8589 | AO74: 8589 | AP74: 9174070 | AQ74: ANTONIO | AR74: FEIJOO | AS74: NULL | AT74: NULL | AU74: Cancelled | AV74: Cancelled | AW74: 46023 | AX74: 46023 | AY74: 45947 | AZ74: 45947 | BA74: 46034 | BB74: 46023 | BC74: 46023 | BD74: 45947 | BE74: 46034 | BF74: 45934 | BG74: 46034
A75: 2026 | B75: 46204 | C75: 177423 | D75: 104.02 | E75: 7625307 | F75: 5141074074 | G75: OE | H75: EDE | I75: EN | J75: Dental | K75: 211322179 | L75: 1000293590 | M75: =VLOOKUP(L75,Selma!H$1:H$3913,1,FALSE) -> 1000293590 | N75: In Selma's report | O75: Subscriber | P75: Self | Q75: Active Re-enrollee | R75: 23305 | S75: Mattie | T75: Johnson | U75: 17.74 | V75: 17.74 | W75: 17.74 | X75: NULL | Y75: NULL | Z75: APTC_CSR | AA75: LOW | AB75: 83502GA002000801 | AC75: 3634 | AD75: Best Life Essential Basic Dental Plan | AE75: 83502 | AF75: BEST Life and Health Insurance Company | AG75: 62 | AH75: mattieallen123@gmail.com | AI75: 7062248411 | AJ75: 2 | AK75: Clarke | AL75: 30601 | AM75: AGENT | AN75: 1502536 | AO75: 1502536 | AP75: 16906303 | AQ75: Al | AR75: Jones | AS75: HealthSherpa | AT75: HealthSherpa | AU75: Cancelled | AV75: Cancelled | AW75: 46023 | AX75: 46023 | AY75: 45947 | AZ75: 45947 | BA75: 46039 | BB75: 46023 | BC75: 46023 | BD75: 45947 | BE75: 46039 | BF75: 46001 | BG75: 46031
A76: 2026 | B76: 46204 | C76: 193864 | D76: 118.2 | E76: 5747101 | F76: 5422104947 | G76: OE | H76: CN | I76: EN | J76: Dental | K76: 212238524 | L76: 1000320548 | M76: =VLOOKUP(L76,Selma!H$1:H$3913,1,FALSE) -> 1000320548 | N76: In Selma's report | O76: Subscriber | P76: Self | Q76: Automatic Re-enrollee | R76: 32547 | S76: Jacob | T76: Nelson | U76: 22.91 | V76: 51.68 | W76: 51.68 | X76: NULL | Y76: NULL | Z76: APTC_CSR | AA76: LOW | AB76: 83502GA002000601 | AC76: 3632 | AD76: Best Life Essential Value Dental Plan | AE76: 83502 | AF76: BEST Life and Health Insurance Company | AG76: 36 | AH76: jacob291989@gmail.com | AI76: 7063020878 | AJ76: 8 | AK76: Troup | AL76: 30241 | AM76: AGENT | AN76: 2728 | AO76: 2728 | AP76: 17178212 | AQ76: LADALE | AR76: LANE | AS76: HealthSherpa | AT76: HealthSherpa | AU76: Cancelled | AV76: Cancelled | AW76: 46054 | AX76: 46054 | AY76: NULL | AZ76: 46037 | BA76: 46094 | BB76: 46054 | BC76: 46054 | BD76: 46037 | BE76: 46094 | BF76: 45934 | BG76: 46094
A77: 2026 | B77: 46204 | C77: 198879 | D77: 101.31 | E77: 6395828 | F77: 5299648615 | G77: OE | H77: CN | I77: EN | J77: Dental | K77: 212141951 | L77: 1000328949 | M77: =VLOOKUP(L77,Selma!H$1:H$3913,1,FALSE) -> 1000328949 | N77: In Selma's report | O77: Subscriber | P77: Self | Q77: Active Re-enrollee | R77: 33255 | S77: Brittany | T77: Gonzalez | U77: 38.98 | V77: 38.98 | W77: 38.98 | X77: 0 | Y77: NULL | Z77: APTC_CSR | AA77: HIGH | AB77: 83502GA002000301 | AC77: 3631 | AD77: Best Life Superior Dental Plan | AE77: 83502 | AF77: BEST Life and Health Insurance Company | AG77: 35 | AH77: bjackson.18@yahoo.com | AI77: 4049141002 | AJ77: 2 | AK77: Barrow | AL77: 30666 | AM77: AGENT | AN77: 4871 | AO77: 4871 | AP77: 15697046 | AQ77: WITFIELD | AR77: JEAN-BAPTISTE | AS77: HealthSherpa | AT77: HealthSherpa | AU77: Terminated | AV77: Terminated | AW77: 46054 | AX77: 46142 | AY77: 46054 | AZ77: 46023 | BA77: 46186 | BB77: 46054 | BC77: 46142 | BD77: 46023 | BE77: 46186 | BF77: 45934 | BG77: 46023
A78: 2026 | B78: 46204 | C78: 225384 | D78: 115.02 | E78: 5973315 | F78: 5115061861 | G78: OE | H78: CN | I78: EN | J78: Dental | K78: 212179090 | L78: 1000372916 | M78: =VLOOKUP(L78,Selma!H$1:H$3913,1,FALSE) -> 1000372916 | N78: In Selma's report | O78: Subscriber | P78: Self | Q78: Active Re-enrollee | R78: 25960 | S78: Kenya | T78: Johnson | U78: 44.77 | V78: 44.77 | W78: 44.77 | X78: NULL | Y78: NULL | Z78: APTC_CSR | AA78: HIGH | AB78: 83502GA002000301 | AC78: 3631 | AD78: Best Life Superior Dental Plan | AE78: 83502 | AF78: BEST Life and Health Insurance Company | AG78: 55 | AH78: johnsonkenya19@yahoo.com | AI78: 3476042338 | AJ78: 3 | AK78: DEKALB | AL78: 30038 | AM78: AGENT | AN78: 6921 | AO78: 6921 | AP78: 20842475 | AQ78: LEYA | AR78: BELACHEW | AS78: NULL | AT78: NULL | AU78: Enrolled | AV78: Enrolled | AW78: 46054 | AX78: 46387 | AY78: 46050 | AZ78: 46031 | BA78: 46050 | BB78: 46054 | BC78: 46387 | BD78: 46031 | BE78: 46050 | BF78: 45934 | BG78: 46031
A79: 2026 | B79: 46204 | C79: 229605 | D79: 100.05 | E79: 7833010 | F79: 5145476766 | G79: OE | H79: ON | I79: EN | J79: Dental | K79: 212226255 | L79: 1000380035 | M79: =VLOOKUP(L79,Selma!H$1:H$3913,1,FALSE) -> 1000380035 | N79: In Selma's report | O79: Subscriber | P79: Self | Q79: New Consumer | R79: 27785 | S79: Corey | T79: Pitts | U79: 38.23 | V79: 38.23 | W79: 38.23 | X79: NULL | Y79: NULL | Z79: APTC_CSR | AA79: HIGH | AB79: 83502GA002000301 | AC79: 3631 | AD79: Best Life Superior Dental Plan | AE79: 83502 | AF79: BEST Life and Health Insurance Company | AG79: 50 | AH79: pittsmobiletire@gmail.com | AI79: 2292568961 | AJ79: 1 | AK79: Sumter | AL79: 31709 | AM79: AGENT | AN79: 1736 | AO79: 1736 | AP79: 4649559 | AQ79: ANGELA | AR79: BOVELL | AS79: HealthSherpa | AT79: HealthSherpa | AU79: Cancelled | AV79: Cancelled | AW79: 46054 | AX79: 46054 | AY79: NULL | AZ79: 46037 | BA79: 46191 | BB79: 46054 | BC79: 46054 | BD79: 46037 | BE79: 46191 | BF79: 46008 | BG79: 46191
A80: 2026 | B80: 46204 | C80: 229605 | D80: 100.05 | E80: 7833010 | F80: 5145476766 | G80: OE | H80: ON | I80: EN | J80: Dental | K80: 212223856 | L80: 1000380035 | M80: =VLOOKUP(L80,Selma!H$1:H$3913,1,FALSE) -> 1000380035 | N80: In Selma's report | O80: Subscriber | P80: Self | Q80: New Consumer | R80: 27785 | S80: Corey | T80: Pitts | U80: 38.23 | V80: 74.02 | W80: 74.02 | X80: NULL | Y80: NULL | Z80: APTC_CSR | AA80: HIGH | AB80: 83502GA002000301 | AC80: 3631 | AD80: Best Life Superior Dental Plan | AE80: 83502 | AF80: BEST Life and Health Insurance Company | AG80: 50 | AH80: pittsmobiletire@gmail.com | AI80: 2292568961 | AJ80: 1 | AK80: Sumter | AL80: 31709 | AM80: AGENT | AN80: 1736 | AO80: 1736 | AP80: 4649559 | AQ80: ANGELA | AR80: BOVELL | AS80: HealthSherpa | AT80: HealthSherpa | AU80: Cancelled | AV80: Cancelled | AW80: 46054 | AX80: 46054 | AY80: NULL | AZ80: 46037 | BA80: 46037 | BB80: 46054 | BC80: 46054 | BD80: 46037 | BE80: 46037 | BF80: 46008 | BG80: 46191
A81: 2026 | B81: 46204 | C81: 294008 | D81: 108.63 | E81: 8266911 | F81: 5130014028 | G81: SEP | H81: ON | I81: EN | J81: Dental | K81: 211705656 | L81: 1000487232 | M81: =VLOOKUP(L81,Selma!H$1:H$3913,1,FALSE) -> 1000487232 | N81: In Selma's report | O81: Subscriber | P81: Self | Q81: Active Re-enrollee | R81: 27521 | S81: Charles | T81: Williams | U81: 30.9 | V81: 30.9 | W81: 30.9 | X81: NULL | Y81: NULL | Z81: APTC_CSR | AA81: HIGH | AB81: 83502GA002000701 | AC81: 3633 | AD81: Best Life Preferred Dental Plan | AE81: 83502 | AF81: BEST Life and Health Insurance Company | AG81: 50 | AH81: cw3768320@gmail.com | AI81: 4783880569 | AJ81: 12 | AK81: Houston | AL81: 31088 | AM81: AGENT | AN81: 5159 | AO81: 5159 | AP81: 20087176 | AQ81: JAMAL | AR81: SHUMAN | AS81: HealthSherpa | AT81: HealthSherpa | AU81: Cancelled | AV81: Cancelled | AW81: 46023 | AX81: 46023 | AY81: NULL | AZ81: 45978 | BA81: 46065 | BB81: 46023 | BC81: 46023 | BD81: 45978 | BE81: 46065 | BF81: 46044 | BG81: 46065
A82: 2026 | B82: 46204 | C82: 299737 | D82: 108.58 | E82: 9084416 | F82: 5915374172 | G82: QEP | H82: ON | I82: EN | J82: Dental | K82: 1000204372 | L82: 1000496452 | M82: =VLOOKUP(L82,Selma!H$1:H$3913,1,FALSE) -> #N/A | N82: Not in Selma's report | O82: Subscriber | P82: Self | Q82: New Consumer | R82: 32400 | S82: Chelsea | T82: Person | U82: 44.77 | V82: 44.77 | W82: 44.77 | X82: NULL | Y82: NULL | Z82: APTC_CSR | AA82: HIGH | AB82: 83502GA002000301 | AC82: 3631 | AD82: Best Life Superior Dental Plan | AE82: 83502 | AF82: BEST Life and Health Insurance Company | AG82: 37 | AH82: person.chelsea@gmail.com | AI82: 7702766009 | AJ82: 3 | AK82: Clayton | AL82: 30238 | AM82: AGENT | AN82: 1728719 | AO82: 1728719 | AP82: 18124018 | AQ82: Teshamarie | AR82: Espinoza | AS82: HealthSherpa | AT82: HealthSherpa | AU82: Pending | AV82: Pending | AW82: 46174 | AX82: 46387 | AY82: NULL | AZ82: 46148 | BA82: 46148 | BB82: 46174 | BC82: 46387 | BD82: 46148 | BE82: 46148 | BF82: 46147 | BG82: 46148
A83: 2026 | B83: 46204 | C83: 302619 | D83: 122.65 | E83: 7791107 | F83: 5119352248 | G83: OE | H83: ON | I83: EN | J83: Dental | K83: 212241227 | L83: 1000501354 | M83: =VLOOKUP(L83,Selma!H$1:H$3913,1,FALSE) -> 1000501354 | N83: In Selma's report | O83: Subscriber | P83: Self | Q83: Active Re-enrollee | R83: 34939 | S83: Abigrace | T83: Diprima | U83: 36.67 | V83: 36.67 | W83: 36.67 | X83: 0 | Y83: NULL | Z83: APTC_CSR | AA83: HIGH | AB83: 83502GA002000701 | AC83: 3633 | AD83: Best Life Preferred Dental Plan | AE83: 83502 | AF83: BEST Life and Health Insurance Company | AG83: 30 | AH83: abigracediprima@gmail.com | AI83: 6788369602 | AJ83: 3 | AK83: Dekalb | AL83: 30329 | AM83: AGENT | AN83: 1331391 | AO83: 1331391 | AP83: 21386680 | AQ83: Kerry | AR83: Turney | AS83: NULL | AT83: NULL | AU83: Enrolled | AV83: Enrolled | AW83: 46054 | AX83: 46387 | AY83: 46086 | AZ83: 46037 | BA83: 46086 | BB83: 46054 | BC83: 46387 | BD83: 46037 | BE83: 46086 | BF83: 46006 | BG83: 46037
A84: 2026 | B84: 46204 | C84: 323288 | D84: 102.77 | E84: 9313815 | F84: GAT50175098 | G84: QEP | H84: EDE | I84: EN | J84: Dental | K84: 212061197 | L84: 1000534782 | M84: =VLOOKUP(L84,Selma!H$1:H$3913,1,FALSE) -> 1000534782 | N84: In Selma's report | O84: Subscriber | P84: Self | Q84: Active Re-enrollee | R84: 26104 | S84: MAURICE | T84: MUHAMMAD | U84: 38.98 | V84: 77.96 | W84: 77.96 | X84: NULL | Y84: NULL | Z84: APTC_CSR | AA84: HIGH | AB84: 83502GA002000301 | AC84: 3631 | AD84: Best Life Superior Dental Plan | AE84: 83502 | AF84: BEST Life and Health Insurance Company | AG84: 54 | AH84: mshaymuhammad1@gmail.com | AI84: 7064240656 | AJ84: 2 | AK84: Oglethorpe | AL84: 30669 | AM84: AGENT | AN84: 3568 | AO84: 3568 | AP84: 17366906 | AQ84: LUIS | AR84: DE LA ROSA | AS84: HealthSherpa | AT84: HealthSherpa | AU84: Cancelled | AV84: Cancelled | AW84: 46023 | AX84: 46023 | AY84: NULL | AZ84: 46006 | BA84: 46065 | BB84: 46023 | BC84: 46023 | BD84: 46006 | BE84: 46065 | BF84: 46182 | BG84: 46185
A85: 2026 | B85: 46204 | C85: 328969 | D85: 120.38 | E85: 9291722 | F85: 5167824520 | G85: SEP | H85: ON | I85: EN | J85: Dental | K85: 212034099 | L85: 1000544816 | M85: =VLOOKUP(L85,Selma!H$1:H$3913,1,FALSE) -> 1000544816 | N85: In Selma's report | O85: Subscriber | P85: Self | Q85: Active Re-enrollee | R85: 27015 | S85: Shanika | T85: Wesley | U85: 39.79 | V85: 79.58 | W85: 79.58 | X85: 0 | Y85: NULL | Z85: APTC_CSR | AA85: HIGH | AB85: 83502GA002000301 | AC85: 3631 | AD85: Best Life Superior Dental Plan | AE85: 83502 | AF85: BEST Life and Health Insurance Company | AG85: 52 | AH85: shanika314wesley@gmail.com | AI85: 7708758935 | AJ85: 8 | AK85: Troup | AL85: 30241 | AM85: AGENT | AN85: 8484 | AO85: 8484 | AP85: 19237196 | AQ85: NANA | AR85: NASH | AS85: HealthSherpa | AT85: HealthSherpa | AU85: Cancelled | AV85: Cancelled | AW85: 46023 | AX85: 46023 | AY85: NULL | AZ85: 46006 | BA85: 46065 | BB85: 46023 | BC85: 46023 | BD85: 46006 | BE85: 46065 | BF85: 46177 | BG85: 46177
A86: 2026 | B86: 46204 | C86: 330607 | D86: 102.24 | E86: 7548608 | F86: 5123366787 | G86: OE | H86: EDE | I86: EN | J86: Dental | K86: 211189138 | L86: 1000547860 | M86: =VLOOKUP(L86,Selma!H$1:H$3913,1,FALSE) -> 1000547860 | N86: In Selma's report | O86: Subscriber | P86: Self | Q86: Active Re-enrollee | R86: 28395 | S86: ALICE | T86: KESSE | U86: 20.37 | V86: 20.37 | W86: 20.37 | X86: NULL | Y86: NULL | Z86: APTC_CSR | AA86: LOW | AB86: 83502GA002000801 | AC86: 3634 | AD86: Best Life Essential Basic Dental Plan | AE86: 83502 | AF86: BEST Life and Health Insurance Company | AG86: 48 | AH86: tonikempireinc@gmail.com | AI86: 9173615116 | AJ86: 3 | AK86: Fulton | AL86: 30312 | AM86: AGENT | AN86: 4256 | AO86: 4256 | AP86: 16914169 | AQ86: GREGORY | AR86: ALLEN | AS86: HealthSherpa | AT86: HealthSherpa | AU86: Cancelled | AV86: Cancelled | AW86: 46023 | AX86: 46023 | AY86: 45946 | AZ86: 45946 | BA86: 46000 | BB86: 46023 | BC86: 46023 | BD86: 45946 | BE86: 46000 | BF86: 45997 | BG86: 46000
A87: 2026 | B87: 46204 | C87: 376722 | D87: 108.82 | E87: 5635057 | F87: 5308338546 | G87: OE | H87: CN | I87: EN | J87: Dental | K87: 210659907 | L87: 1000623918 | M87: =VLOOKUP(L87,Selma!H$1:H$3913,1,FALSE) -> 1000623918 | N87: In Selma's report | O87: Subscriber | P87: Spouse | Q87: Active Re-enrollee | R87: 23224 | S87: Kayode | T87: Adekunle | U87: 44.77 | V87: 98.49 | W87: 98.49 | X87: NULL | Y87: NULL | Z87: APTC_CSR | AA87: HIGH | AB87: 83502GA002000301 | AC87: 3631 | AD87: Best Life Superior Dental Plan | AE87: 83502 | AF87: BEST Life and Health Insurance Company | AG87: 62 | AH87: hkmcare@pm.me | AI87: 7707224819 | AJ87: 3 | AK87: ROCKDALE | AL87: 30094 | AM87: AGENT | AN87: 548527 | AO87: 548527 | AP87: 9126142 | AQ87: BRENDA J | AR87: GONZALEZ | AS87: NULL | AT87: NULL | AU87: Cancelled | AV87: Cancelled | AW87: 46023 | AX87: 46023 | AY87: 45946 | AZ87: 45946 | BA87: 46061 | BB87: 46023 | BC87: 46023 | BD87: 45946 | BE87: 46061 | BF87: 45934 | BG87: 46061
A88: 2026 | B88: 46204 | C88: 389968 | D88: 105.43 | E88: 8191022 | F88: 5135735515 | G88: OE | H88: EDE | I88: EN | J88: Dental | K88: 211339868 | L88: 1000645766 | M88: =VLOOKUP(L88,Selma!H$1:H$3913,1,FALSE) -> 1000645766 | N88: In Selma's report | O88: Subscriber | P88: Self | Q88: Active Re-enrollee | R88: 25223 | S88: Laquisha | T88: Marion | U88: 20.37 | V88: 20.37 | W88: 20.37 | X88: 0 | Y88: NULL | Z88: APTC_CSR | AA88: LOW | AB88: 83502GA002000801 | AC88: 3634 | AD88: Best Life Essential Basic Dental Plan | AE88: 83502 | AF88: BEST Life and Health Insurance Company | AG88: 57 | AH88: laquishamarion@gmail.com | AI88: 6789075587 | AJ88: 3 | AK88: DeKalb | AL88: 30035 | AM88: AGENT | AN88: 551490 | AO88: 551490 | AP88: 21128074 | AQ88: JOSEPH ALEXANDER | AR88: CABRERA | AS88: HealthSherpa | AT88: HealthSherpa | AU88: Enrolled | AV88: Enrolled | AW88: 46023 | AX88: 46387 | AY88: 45947 | AZ88: 45947 | BA88: 46037 | BB88: 46023 | BC88: 46387 | BD88: 45947 | BE88: 46037 | BF88: 46037 | BG88: 46037
A89: 2026 | B89: 46204 | C89: 391503 | D89: 103.19 | E89: 8951159 | F89: 5135379489 | G89: SEP | H89: ON | I89: EN | J89: Dental | K89: 211064215 | L89: 1000648053 | M89: =VLOOKUP(L89,Selma!H$1:H$3913,1,FALSE) -> 1000648053 | N89: In Selma's report | O89: Subscriber | P89: Self | Q89: Active Re-enrollee | R89: 25185 | S89: Feli'cia | T89: Gibson | U89: 20.37 | V89: 20.37 | W89: 20.37 | X89: NULL | Y89: NULL | Z89: APTC_CSR | AA89: LOW | AB89: 83502GA002000801 | AC89: 3634 | AD89: Best Life Essential Basic Dental Plan | AE89: 83502 | AF89: BEST Life and Health Insurance Company | AG89: 57 | AH89: fgibson003@gmail.com | AI89: 6785239773 | AJ89: 3 | AK89: HENRY | AL89: 30228 | AM89: AGENT | AN89: 547478 | AO89: 547478 | AP89: 13976603 | AQ89: JIMMY R | AR89: JALIL | AS89: NULL | AT89: NULL | AU89: Enrolled | AV89: Enrolled | AW89: 46023 | AX89: 46387 | AY89: 45946 | AZ89: 45946 | BA89: 46126 | BB89: 46023 | BC89: 46387 | BD89: 45946 | BE89: 46126 | BF89: 46126 | BG89: 46126
A90: 2026 | B90: 46204 | C90: 398515 | D90: 107.35 | E90: 8033214 | F90: 5130251942 | G90: SEP | H90: ON | I90: EN | J90: Dental | K90: 211054183 | L90: 1000659728 | M90: =VLOOKUP(L90,Selma!H$1:H$3913,1,FALSE) -> 1000659728 | N90: In Selma's report | O90: Subscriber | P90: Self | Q90: New Consumer | R90: 30346 | S90: christy | T90: streetman | U90: 17.74 | V90: 17.74 | W90: 17.74 | X90: NULL | Y90: NULL | Z90: APTC_CSR | AA90: LOW | AB90: 83502GA002000801 | AC90: 3634 | AD90: Best Life Essential Basic Dental Plan | AE90: 83502 | AF90: BEST Life and Health Insurance Company | AG90: 42 | AH90: gypsychic30@gmail.com | AI90: 6786303400 | AJ90: 2 | AK90: JACKSON | AL90: 30558 | AM90: AGENT | AN90: 550395 | AO90: 550395 | AP90: 6766554 | AQ90: GINGER H | AR90: REEVES | AS90: NULL | AT90: NULL | AU90: Terminated | AV90: Terminated | AW90: 46023 | AX90: 46053 | AY90: 45946 | AZ90: 45946 | BA90: 46035 | BB90: 46023 | BC90: 46053 | BD90: 45946 | BE90: 46035 | BF90: 46024 | BG90: 46036
A91: 2026 | B91: 46204 | C91: 398575 | D91: 120.57 | E91: 5801548 | F91: 5131894152 | G91: OE | H91: CN | I91: EN | J91: Dental | K91: 210631260 | L91: 1000659778 | M91: =VLOOKUP(L91,Selma!H$1:H$3913,1,FALSE) -> 1000659778 | N91: In Selma's report | O91: Subscriber | P91: Self | Q91: Automatic Re-enrollee | R91: 28452 | S91: Evelia | T91: Marquez Andablo | U91: 16.72 | V91: 33.44 | W91: 33.44 | X91: NULL | Y91: NULL | Z91: APTC_CSR | AA91: LOW | AB91: 83502GA002000801 | AC91: 3634 | AD91: Best Life Essential Basic Dental Plan | AE91: 83502 | AF91: BEST Life and Health Insurance Company | AG91: 48 | AH91: evelia1977@icloud.com | AI91: 7069805280 | AJ91: 9 | AK91: WHITFIELD | AL91: 30720 | AM91: AGENT | AN91: 1760344 | AO91: 1760344 | AP91: 17437412 | AQ91: Roberto | AR91: Gutierrez Plazarte | AS91: NULL | AT91: NULL | AU91: Cancelled | AV91: Cancelled | AW91: 46023 | AX91: 46023 | AY91: 45946 | AZ91: 45946 | BA91: 46190 | BB91: 46023 | BC91: 46023 | BD91: 45946 | BE91: 46190 | BF91: 45934 | BG91: 45984
A92: 2026 | B92: 46204 | C92: 399458 | D92: 115.17 | E92: 5604566 | F92: 5562333787 | G92: OE | H92: CN | I92: EN | J92: Dental | K92: 212122776 | L92: 1000661327 | M92: =VLOOKUP(L92,Selma!H$1:H$3913,1,FALSE) -> 1000661327 | N92: In Selma's report | O92: Subscriber | P92: Self | Q92: Automatic Re-enrollee | R92: 33276 | S92: Xavier | T92: Maddox | U92: 44.77 | V92: 44.77 | W92: 44.77 | X92: NULL | Y92: NULL | Z92: APTC_CSR | AA92: HIGH | AB92: 83502GA002000301 | AC92: 3631 | AD92: Best Life Superior Dental Plan | AE92: 83502 | AF92: BEST Life and Health Insurance Company | AG92: 34 | AH92: maddoxx46@gmail.com | AI92: 4048074590 | AJ92: 3 | AK92: Cobb | AL92: 30008 | AM92: AGENT | AN92: 11389 | AO92: 11389 | AP92: 19302669 | AQ92: WILLIAM | AR92: HEWITT | AS92: MyMFG | AT92: MyMFG | AU92: Enrolled | AV92: Enrolled | AW92: 46054 | AX92: 46387 | AY92: 46058 | AZ92: 46020 | BA92: 46058 | BB92: 46054 | BC92: 46387 | BD92: 46020 | BE92: 46058 | BF92: 45934 | BG92: 46020
A93: 2026 | B93: 46204 | C93: 399762 | D93: 102.21 | E93: 5805251 | F93: 5398152957 | G93: OE | H93: CN | I93: EN | J93: Dental | K93: 212019794 | L93: 1000661834 | M93: =VLOOKUP(L93,Selma!H$1:H$3913,1,FALSE) -> 1000661834 | N93: In Selma's report | O93: Subscriber | P93: Self | Q93: Active Re-enrollee | R93: 33229 | S93: Damon | T93: Smith | U93: 44.77 | V93: 44.77 | W93: 44.77 | X93: NULL | Y93: NULL | Z93: APTC_CSR | AA93: HIGH | AB93: 83502GA002000301 | AC93: 3631 | AD93: Best Life Superior Dental Plan | AE93: 83502 | AF93: BEST Life and Health Insurance Company | AG93: 35 | AH93: damonsmith001@icloud.com | AI93: 6785162988 | AJ93: 3 | AK93: DEKALB | AL93: 30079 | AM93: AGENT | AN93: 553024 | AO93: 553024 | AP93: 19593898 | AQ93: LATISHA MONIQUE | AR93: JONES | AS93: NULL | AT93: NULL | AU93: Cancelled | AV93: Cancelled | AW93: 46023 | AX93: 46023 | AY93: NULL | AZ93: 46006 | BA93: 46065 | BB93: 46023 | BC93: 46023 | BD93: 46006 | BE93: 46065 | BF93: 45934 | BG93: 46065
A94: 2026 | B94: 46204 | C94: 404144 | D94: 122.21 | E94: 9201487 | F94: 5535481311 | G94: SEP | H94: ON | I94: EN | J94: Dental | K94: 212243504 | L94: 1000669121 | M94: =VLOOKUP(L94,Selma!H$1:H$3913,1,FALSE) -> 1000669121 | N94: In Selma's report | O94: Subscriber | P94: Self | Q94: Automatic Re-enrollee | R94: 31062 | S94: Letrisha | T94: Chatman | U94: 20.37 | V94: 20.37 | W94: 20.37 | X94: NULL | Y94: NULL | Z94: APTC_CSR | AA94: LOW | AB94: 83502GA002000801 | AC94: 3634 | AD94: Best Life Essential Basic Dental Plan | AE94: 83502 | AF94: BEST Life and Health Insurance Company | AG94: 41 | AH94: trisha626730@hotmail.com | AI94: 4048398299 | AJ94: 3 | AK94: DEKALB | AL94: 30038 | AM94: AGENT | AN94: 1167669 | AO94: 1167669 | AP94: 21390951 | AQ94: AMAAN | AR94: LALANI | AS94: NULL | AT94: NULL | AU94: Terminated | AV94: Terminated | AW94: 46054 | AX94: 46081 | AY94: 46043 | AZ94: 46037 | BA94: 46162 | BB94: 46054 | BC94: 46081 | BD94: 46037 | BE94: 46162 | BF94: 46162 | BG94: 46162
A95: 2026 | B95: 46204 | C95: 417958 | D95: 115.02 | E95: 5845722 | F95: 5365074588 | G95: OE | H95: CN | I95: EN | J95: Dental | K95: 212097058 | L95: 1000692023 | M95: =VLOOKUP(L95,Selma!H$1:H$3913,1,FALSE) -> 1000692023 | N95: In Selma's report | O95: Subscriber | P95: Self | Q95: Active Re-enrollee | R95: 30022 | S95: LeAnn | T95: Leagans | U95: 20.37 | V95: 20.37 | W95: 20.37 | X95: 0 | Y95: NULL | Z95: APTC_CSR | AA95: LOW | AB95: 83502GA002000801 | AC95: 3634 | AD95: Best Life Essential Basic Dental Plan | AE95: 83502 | AF95: BEST Life and Health Insurance Company | AG95: 43 | AH95: leann.leagans@me.com | AI95: 6786623566 | AJ95: 3 | AK95: Fulton | AL95: 30268 | AM95: AGENT | AN95: 3292 | AO95: 3292 | AP95: 20093310 | AQ95: EDISON | AR95: MACKLEY | AS95: NULL | AT95: NULL | AU95: Enrolled | AV95: Enrolled | AW95: 46054 | AX95: 46387 | AY95: 46026 | AZ95: 46013 | BA95: 46026 | BB95: 46054 | BC95: 46387 | BD95: 46013 | BE95: 46026 | BF95: 45934 | BG95: 46013
A96: 2026 | B96: 46204 | C96: 430403 | D96: 106.15 | E96: 8774308 | F96: 5167749839 | G96: SEP | H96: RR | I96: EN | J96: Dental | K96: 212059681 | L96: 1000712450 | M96: =VLOOKUP(L96,Selma!H$1:H$3913,1,FALSE) -> 1000712450 | N96: In Selma's report | O96: Subscriber | P96: Self | Q96: New Consumer | R96: 32539 | S96: Sana | T96: bhatti | U96: 44.77 | V96: 89.54 | W96: 89.54 | X96: NULL | Y96: NULL | Z96: APTC_CSR | AA96: HIGH | AB96: 83502GA002000301 | AC96: 3631 | AD96: Best Life Superior Dental Plan | AE96: 83502 | AF96: BEST Life and Health Insurance Company | AG96: 36 | AH96: lokhandwalasana@gmail.com | AI96: 4043339846 | AJ96: 3 | AK96: NULL | AL96: 30040 | AM96: AGENT | AN96: 9436 | AO96: 9436 | AP96: 20457319 | AQ96: CHARITY | AR96: GILLESPIE | AS96: NULL | AT96: NULL | AU96: Terminated | AV96: Terminated | AW96: 46023 | AX96: 46142 | AY96: 46032 | AZ96: 46006 | BA96: 46186 | BB96: 46023 | BC96: 46142 | BD96: 46006 | BE96: 46186 | BF96: 46100 | BG96: 46139
A97: 2026 | B97: 46204 | C97: 460414 | D97: 104.02 | E97: 6393582 | F97: 5124047739 | G97: OE | H97: CN | I97: EN | J97: Dental | K97: 211182945 | L97: 1000762299 | M97: =VLOOKUP(L97,Selma!H$1:H$3913,1,FALSE) -> 1000762299 | N97: In Selma's report | O97: Subscriber | P97: Self | Q97: Active Re-enrollee | R97: 23849 | S97: Carmel | T97: Filberg | U97: 36.67 | V97: 36.67 | W97: 36.67 | X97: NULL | Y97: NULL | Z97: APTC_CSR | AA97: HIGH | AB97: 83502GA002000701 | AC97: 3633 | AD97: Best Life Preferred Dental Plan | AE97: 83502 | AF97: BEST Life and Health Insurance Company | AG97: 60 | AH97: ccfilberg@gmail.com | AI97: 6788828791 | AJ97: 3 | AK97: FULTON | AL97: 30022 | AM97: AGENT | AN97: 867835 | AO97: 867835 | AP97: 21336646 | AQ97: Lindsay | AR97: Dougherty | AS97: Centene-Ambetter | AT97: HealthSherpa | AU97: Enrolled | AV97: Enrolled | AW97: 46023 | AX97: 46387 | AY97: 45946 | AZ97: 45946 | BA97: 46002 | BB97: 46023 | BC97: 46387 | BD97: 45946 | BE97: 46002 | BF97: 45934 | BG97: 46008
A98: 2026 | B98: 46204 | C98: 461424 | D98: 123.83 | E98: 9252552 | F98: 5966278422 | G98: SEP | H98: ON | I98: EN | J98: Dental | K98: 212174639 | L98: 1003536430 | M98: =VLOOKUP(L98,Selma!H$1:H$3913,1,FALSE) -> 1003536430 | N98: In Selma's report | O98: Subscriber | P98: Child | Q98: Active Re-enrollee | R98: 36952 | S98: Jadah | T98: Thomas | U98: 24.12 | V98: 24.12 | W98: 24.12 | X98: NULL | Y98: NULL | Z98: QHP | AA98: LOW | AB98: 83502GA002000601 | AC98: 3632 | AD98: Best Life Essential Value Dental Plan | AE98: 83502 | AF98: BEST Life and Health Insurance Company | AG98: 24 | AH98: latasha.cash@wjdpbh.com | AI98: 4044825140 | AJ98: 3 | AK98: Fulton | AL98: 30344 | AM98: AGENT | AN98: 8198 | AO98: 8198 | AP98: 21117640 | AQ98: MICHAEL | AR98: NOELUS | AS98: HealthSherpa | AT98: HealthSherpa | AU98: Cancelled | AV98: Cancelled | AW98: 46054 | AX98: 46054 | AY98: NULL | AZ98: 46030 | BA98: 46094 | BB98: 46054 | BC98: 46054 | BD98: 46030 | BE98: 46094 | BF98: 46171 | BG98: 46171
A99: 2026 | B99: 46204 | C99: 467246 | D99: 123.35 | E99: 7559930 | F99: 5118844799 | G99: SEP | H99: ON | I99: EN | J99: Dental | K99: 211002985 | L99: 1000773602 | M99: =VLOOKUP(L99,Selma!H$1:H$3913,1,FALSE) -> 1000773602 | N99: In Selma's report | O99: Subscriber | P99: Self | Q99: Active Re-enrollee | R99: 27413 | S99: ADDIS | T99: KETSELA | U99: 25.77 | V99: 51.54 | W99: 51.54 | X99: NULL | Y99: NULL | Z99: APTC_CSR | AA99: LOW | AB99: 83502GA002000601 | AC99: 3632 | AD99: Best Life Essential Value Dental Plan | AE99: 83502 | AF99: BEST Life and Health Insurance Company | AG99: 50 | AH99: aketsela@hotmail.com | AI99: 4048496808 | AJ99: 3 | AK99: GWINNETT | AL99: 30084 | AM99: AGENT | AN99: 551610 | AO99: 551610 | AP99: 17028382 | AQ99: JORGO | AR99: LEMMA | AS99: NULL | AT99: NULL | AU99: Terminated | AV99: Terminated | AW99: 46023 | AX99: 46203 | AY99: 45946 | AZ99: 45946 | BA99: 46176 | BB99: 46023 | BC99: 46203 | BD99: 45946 | BE99: 46176 | BF99: 45999 | BG99: 46003
A100: 2026 | B100: 46204 | C100: 475175 | D100: 108.63 | E100: 5632643 | F100: 5145509429 | G100: OE | H100: CN | I100: EN | J100: Dental | K100: 211224591 | L100: 1000786794 | M100: =VLOOKUP(L100,Selma!H$1:H$3913,1,FALSE) -> 1000786794 | N100: In Selma's report | O100: Subscriber | P100: Self | Q100: Automatic Re-enrollee | R100: 22881 | S100: Tony | T100: Collins | U100: 17.17 | V100: 17.17 | W100: 17.17 | X100: NULL | Y100: NULL | Z100: APTC_CSR | AA100: LOW | AB100: 83502GA002000801 | AC100: 3634 | AD100: Best Life Essential Basic Dental Plan | AE100: 83502 | AF100: BEST Life and Health Insurance Company | AG100: 63 | AH100: tlcollins644@gmail.com | AI100: 4783708301 | AJ100: 12 | AK100: JONES | AL100: 31032 | AM100: AGENT | AN100: 720 | AO100: 720 | AP100: 18205745 | AQ100: PAOLA | AR100: FRITZ | AS100: Centene-Ambetter | AT100: HealthSherpa | AU100: Enrolled | AV100: Enrolled | AW100: 46023 | AX100: 46387 | AY100: 45946 | AZ100: 45946 | BA100: 46093 | BB100: 46023 | BC100: 46387 | BD100: 45946 | BE100: 46093 | BF100: 45934 | BG100: 46093
A101: 2026 | B101: 46204 | C101: 479689 | D101: 104.02 | E101: 8541156 | F101: 5178052136 | G101: QEP | H101: EDE | I101: EN | J101: Dental | K101: 1000048757 | L101: 1000794181 | M101: =VLOOKUP(L101,Selma!H$1:H$3913,1,FALSE) -> 1000794181 | N101: In Selma's report | O101: Subscriber | P101: Self | Q101: Active Re-enrollee | R101: 28917 | S101: Ruthy | T101: Haney Wynn | U101: 21.71 | V101: 21.71 | W101: 21.71 | X101: 0 | Y101: NULL | Z101: APTC_CSR | AA101: LOW | AB101: 83502GA002000601 | AC101: 3632 | AD101: Best Life Essential Value Dental Plan | AE101: 83502 | AF101: BEST Life and Health Insurance Company | AG101: 46 | AH101: ruthyhaney@gmail.com | AI101: 4784209624 | AJ101: 12 | AK101: Bibb | AL101: 31206 | AM101: AGENT | AN101: 552938 | AO101: 552938 | AP101: 20728814 | AQ101: Nicholas | AR101: Labbato | AS101: HealthSherpa | AT101: HealthSherpa | AU101: Cancelled | AV101: Cancelled | AW101: 46082 | AX101: 46082 | AY101: NULL | AZ101: 46071 | BA101: 46124 | BB101: 46082 | BC101: 46082 | BD101: 46071 | BE101: 46124 | BF101: 46071 | BG101: 46124
A102: 2026 | B102: 46204 | C102: 490051 | D102: 102.21 | E102: 7845958 | F102: 5149876528 | G102: OE | H102: EDE | I102: EN | J102: Dental | K102: 211228748 | L102: 1000811411 | M102: =VLOOKUP(L102,Selma!H$1:H$3913,1,FALSE) -> 1000811411 | N102: In Selma's report | O102: Subscriber | P102: Self | Q102: Active Re-enrollee | R102: 24005 | S102: Melissa | T102: Salgado | U102: 44.77 | V102: 44.77 | W102: 44.77 | X102: NULL | Y102: NULL | Z102: APTC_CSR | AA102: HIGH | AB102: 83502GA002000301 | AC102: 3631 | AD102: Best Life Superior Dental Plan | AE102: 83502 | AF102: BEST Life and Health Insurance Company | AG102: 60 | AH102: mv5009@yahoo.com | AI102: 7082241286 | AJ102: 3 | AK102: Douglas | AL102: 30122 | AM102: AGENT | AN102: 1063 | AO102: 1063 | AP102: 19339124 | AQ102: ANDREA | AR102: GONZALEZ QUINTERO | AS102: HealthSherpa | AT102: HealthSherpa | AU102: Cancelled | AV102: Cancelled | AW102: 46023 | AX102: 46023 | AY102: 45946 | AZ102: 45946 | BA102: 46009 | BB102: 46023 | BC102: 46023 | BD102: 45946 | BE102: 46009 | BF102: 46009 | BG102: 46009
A103: 2026 | B103: 46204 | C103: 491018 | D103: 106.13 | E103: 8158482 | F103: 5169314987 | G103: SEP | H103: ON | I103: EN | J103: Dental | K103: 211534077 | L103: 1000812819 | M103: =VLOOKUP(L103,Selma!H$1:H$3913,1,FALSE) -> #N/A | N103: Not in Selma's report | O103: Subscriber | P103: Self | Q103: Active Re-enrollee | R103: 33171 | S103: ANITA | T103: MCINTOSH | U103: 44.77 | V103: 44.77 | W103: 44.77 | X103: NULL | Y103: NULL | Z103: APTC_CSR | AA103: HIGH | AB103: 83502GA002000301 | AC103: 3631 | AD103: Best Life Superior Dental Plan | AE103: 83502 | AF103: BEST Life and Health Insurance Company | AG103: 35 | AH103: ladyempressco@gmail.com | AI103: 7542343529 | AJ103: 3 | AK103: Fulton | AL103: 30350 | AM103: AGENT | AN103: 550229 | AO103: 550229 | AP103: 20517688 | AQ103: MICHAEL | AR103: SANGUILY | AS103: NULL | AT103: NULL | AU103: Enrolled | AV103: Enrolled | AW103: 46023 | AX103: 46387 | AY103: 45947 | AZ103: 45947 | BA103: 46035 | BB103: 46023 | BC103: 46387 | BD103: 45947 | BE103: 46035 | BF103: 46035 | BG103: 46035
A104: 2026 | B104: 46204 | C104: 495697 | D104: 113.48 | E104: 9172223 | F104: 5113756395 | G104: SEP | H104: ON | I104: EN | J104: Dental | K104: 211091128 | L104: 1000820826 | M104: =VLOOKUP(L104,Selma!H$1:H$3913,1,FALSE) -> 1000820826 | N104: In Selma's report | O104: Subscriber | P104: Self | Q104: Active Re-enrollee | R104: 22594 | S104: Eugene | T104: Osazin | U104: 30.93 | V104: 30.93 | W104: 30.93 | X104: NULL | Y104: NULL | Z104: APTC_CSR | AA104: LOW | AB104: 83502GA002000601 | AC104: 3632 | AD104: Best Life Essential Value Dental Plan | AE104: 83502 | AF104: BEST Life and Health Insurance Company | AG104: 64 | AH104: genejohnson1960@gmail.com | AI104: 2109869896 | AJ104: 3 | AK104: Fulton | AL104: 30344 | AM104: AGENT | AN104: 1361634 | AO104: 1361634 | AP104: 20125858 | AQ104: Uriah | AR104: Bullard | AS104: NULL | AT104: NULL | AU104: Cancelled | AV104: Cancelled | AW104: 46023 | AX104: 46023 | AY104: 45946 | AZ104: 45946 | BA104: 46160 | BB104: 46023 | BC104: 46023 | BD104: 45946 | BE104: 46021 | BF104: 46160 | BG104: 46174
A105: 2026 | B105: 46204 | C105: 518262 | D105: 107.35 | E105: 6528781 | F105: 5125565471 | G105: OE | H105: CN | I105: EN | J105: Dental | K105: 210853433 | L105: 1000858412 | M105: =VLOOKUP(L105,Selma!H$1:H$3913,1,FALSE) -> 1000858412 | N105: In Selma's report | O105: Subscriber | P105: Self | Q105: Active Re-enrollee | R105: 28707 | S105: Mariama | T105: Bah | U105: 44.77 | V105: 44.77 | W105: 44.77 | X105: NULL | Y105: NULL | Z105: APTC_CSR | AA105: HIGH | AB105: 83502GA002000301 | AC105: 3631 | AD105: Best Life Superior Dental Plan | AE105: 83502 | AF105: BEST Life and Health Insurance Company | AG105: 47 | AH105: mariamakababah11@gmail.com | AI105: 6783343968 | AJ105: 3 | AK105: Rockdale | AL105: 30058 | AM105: AGENT | AN105: 553105 | AO105: 553105 | AP105: 16574673 | AQ105: OURETIGUI TATI | AR105: KOUYATE | AS105: HealthSherpa | AT105: HealthSherpa | AU105: Cancelled | AV105: Cancelled | AW105: 46023 | AX105: 46023 | AY105: 45946 | AZ105: 45946 | BA105: 46065 | BB105: 46023 | BC105: 46023 | BD105: 45946 | BE105: 46065 | BF105: 45934 | BG105: 46065
A106: 2026 | B106: 46204 | C106: 526060 | D106: 115.02 | E106: 7714537 | F106: 5144043081 | G106: SEP | H106: ON | I106: EN | J106: Dental | K106: 211025345 | L106: 1000871281 | M106: =VLOOKUP(L106,Selma!H$1:H$3913,1,FALSE) -> 1000871281 | N106: In Selma's report | O106: Subscriber | P106: Self | Q106: Active Re-enrollee | R106: 25707 | S106: Tahnesha | T106: Wilson | U106: 20.37 | V106: 20.37 | W106: 20.37 | X106: NULL | Y106: NULL | Z106: APTC_CSR | AA106: LOW | AB106: 83502GA002000801 | AC106: 3634 | AD106: Best Life Essential Basic Dental Plan | AE106: 83502 | AF106: BEST Life and Health Insurance Company | AG106: 55 | AH106: tahnesha@outlook.com | AI106: 4047710164 | AJ106: 3 | AK106: FULTON | AL106: 30318 | AM106: AGENT | AN106: 1126202 | AO106: 1126202 | AP106: 20669803 | AQ106: Ghledya | AR106: Teselle | AS106: Centene-Ambetter | AT106: HealthSherpa | AU106: Cancelled | AV106: Cancelled | AW106: 46023 | AX106: 46023 | AY106: 45946 | AZ106: 45946 | BA106: 46034 | BB106: 46023 | BC106: 46023 | BD106: 45946 | BE106: 46034 | BF106: 46004 | BG106: 46034
A107: 2026 | B107: 46204 | C107: 539023 | D107: 108.07 | E107: 5697753 | F107: 5147309846 | G107: OE | H107: CN | I107: EN | J107: Dental | K107: 212020622 | L107: 1000892868 | M107: =VLOOKUP(L107,Selma!H$1:H$3913,1,FALSE) -> 1000892868 | N107: In Selma's report | O107: Subscriber | P107: Self | Q107: Automatic Re-enrollee | R107: 22496 | S107: John | T107: Olenyik | U107: 27.12 | V107: 27.12 | W107: 27.12 | X107: NULL | Y107: NULL | Z107: APTC_CSR | AA107: LOW | AB107: 83502GA002000601 | AC107: 3632 | AD107: Best Life Essential Value Dental Plan | AE107: 83502 | AF107: BEST Life and Health Insurance Company | AG107: 64 | AH107: gianniola@yahoo.com | AI107: 9125089491 | AJ107: 14 | AK107: CHATHAM | AL107: 31401 | AM107: AGENT | AN107: 4093 | AO107: 4093 | AP107: 18526467 | AQ107: MORGAN | AR107: BLEIN | AS107: NULL | AT107: NULL | AU107: Terminated | AV107: Terminated | AW107: 46023 | AX107: 46081 | AY107: 46010 | AZ107: 46006 | BA107: 46124 | BB107: 46023 | BC107: 46081 | BD107: 46006 | BE107: 46124 | BF107: 45934 | BG107: 46006
A108: 2026 | B108: 46204 | C108: 552747 | D108: 106.38 | E108: 5632143 | F108: 5122123782 | G108: OE | H108: CN | I108: EN | J108: Dental | K108: 211399202 | L108: 1000915889 | M108: =VLOOKUP(L108,Selma!H$1:H$3913,1,FALSE) -> 1000915889 | N108: In Selma's report | O108: Subscriber | P108: Self | Q108: Automatic Re-enrollee | R108: 24224 | S108: Shelia | T108: Walker | U108: 39.79 | V108: 39.79 | W108: 39.79 | X108: NULL | Y108: NULL | Z108: APTC_CSR | AA108: HIGH | AB108: 83502GA002000301 | AC108: 3631 | AD108: Best Life Superior Dental Plan | AE108: 83502 | AF108: BEST Life and Health Insurance Company | AG108: 59 | AH108: NULL | AI108: 7063157744 | AJ108: 8 | AK108: Muscogee | AL108: 31906 | AM108: AGENT | AN108: 548605 | AO108: 548605 | AP108: 6764402 | AQ108: CARL ANTHONY | AR108: BROWN | AS108: HealthSherpa | AT108: HealthSherpa | AU108: Enrolled | AV108: Enrolled | AW108: 46023 | AX108: 46387 | AY108: 45947 | AZ108: 45947 | BA108: 45947 | BB108: 46023 | BC108: 46387 | BD108: 45947 | BE108: 45947 | BF108: 45934 | BG108: 45947
A109: 2026 | B109: 46204 | C109: 572920 | D109: 104.28 | E109: 5664061 | F109: 5320122150 | G109: OE | H109: CN | I109: EN | J109: Dental | K109: 211300042 | L109: 1000949094 | M109: =VLOOKUP(L109,Selma!H$1:H$3913,1,FALSE) -> 1000949094 | N109: In Selma's report | O109: Subscriber | P109: Self | Q109: Active Re-enrollee | R109: 36097 | S109: Kenia | T109: Magana | U109: 20.37 | V109: 20.37 | W109: 20.37 | X109: NULL | Y109: NULL | Z109: APTC_CSR | AA109: LOW | AB109: 83502GA002000801 | AC109: 3634 | AD109: Best Life Essential Basic Dental Plan | AE109: 83502 | AF109: BEST Life and Health Insurance Company | AG109: 27 | AH109: kmagana1029@gmail.com | AI109: 9432130340 | AJ109: 3 | AK109: CLAYTON | AL109: 30274 | AM109: AGENT | AN109: 550976 | AO109: 550976 | AP109: 21114450 | AQ109: HAKAM | AR109: SAFADI | AS109: NULL | AT109: NULL | AU109: Enrolled | AV109: Enrolled | AW109: 46023 | AX109: 46387 | AY109: 45946 | AZ109: 45946 | BA109: 45946 | BB109: 46023 | BC109: 46387 | BD109: 45946 | BE109: 45946 | BF109: 45934 | BG109: 46005
...

Sheet Sheet3
A3: Count of member ID | B3: Column Labels
A4: Row Labels | B4: 2025 | C4: 2026 | D4: Grand Total
A5: In Swathi's report | B5: 1199 | C5: 753 | D5: 1952
A6: Not in Swathi's report | B6: 1772 | C6: 188 | D6: 1960
A7: Grand Total | B7: 2971 | C7: 941 | D7: 3912

Sheet Selma
A1: HIOS ID | B1: Insurance Type | C1: Coveragge Year | D1: Folder Year | E1: Policy Id | F1: Enrollee Id | G1: Health Coverage Policy No | H1: member ID | I1: M ID from Swathi? | J1: M ID in Swathi's report - Status | K1: Issuer indiv identifier | L1: Exchngassigned enrollee id
A2: 83502 | B2: Dental | C2: 2025 | D2: 2025 | E2: 100058 | F2: 1000600684 | G2: 110586889 | H2: 1000600684 | I2: =VLOOKUP(H2,Swathi!L$1:L$1765,1,FALSE) -> 1000600684 | J2: In Swathi's report | K2: 110586889 | L2: NULL
A3: 83502 | B3: Dental | C3: 2025 | D3: 2025 | E3: 1001669 | F3: 1000554900 | G3: 108045704 | H3: 1000554900 | I3: =VLOOKUP(H3,Swathi!L$1:L$1765,1,FALSE) -> 1000554900 | J3: In Swathi's report | K3: 108045704 | L3: NULL
A4: 83502 | B4: Dental | C4: 2025 | D4: 2025 | E4: 1001674 | F4: 1001098323 | G4: 109802612 | H4: 1001098323 | I4: =VLOOKUP(H4,Swathi!L$1:L$1765,1,FALSE) -> #N/A | J4: Not in Swathi's report | K4: 109802612 | L4: NULL
A5: 83502 | B5: Dental | C5: 2025 | D5: 2025 | E5: 100310 | F5: 1001677413 | G5: 110520320 | H5: 1001677413 | I5: =VLOOKUP(H5,Swathi!L$1:L$1765,1,FALSE) -> 1001677413 | J5: In Swathi's report | K5: 110520320 | L5: NULL
A6: 83502 | B6: Dental | C6: 2025 | D6: 2025 | E6: 1003467 | F6: 1001053765 | G6: 110377060 | H6: 1001053765 | I6: =VLOOKUP(H6,Swathi!L$1:L$1765,1,FALSE) -> 1001053765 | J6: In Swathi's report | K6: 110377060 | L6: NULL
A7: 83502 | B7: Dental | C7: 2025 | D7: 2025 | E7: 100572 | F7: 1000467232 | G7: 110672656 | H7: 1000467232 | I7: =VLOOKUP(H7,Swathi!L$1:L$1765,1,FALSE) -> #N/A | J7: Not in Swathi's report | K7: 110672656 | L7: NULL
A8: 83502 | B8: Dental | C8: 2025 | D8: 2025 | E8: 1006308 | F8: 1000306554 | G8: 106285968 | H8: 1000306554 | I8: =VLOOKUP(H8,Swathi!L$1:L$1765,1,FALSE) -> 1000306554 | J8: In Swathi's report | K8: 106285968 | L8: NULL
A9: 83502 | B9: Dental | C9: 2025 | D9: 2025 | E9: 1006497 | F9: 1000917875 | G9: 110300788 | H9: 1000917875 | I9: =VLOOKUP(H9,Swathi!L$1:L$1765,1,FALSE) -> 1000917875 | J9: In Swathi's report | K9: 110300788 | L9: NULL
A10: 83502 | B10: Dental | C10: 2025 | D10: 2025 | E10: 1006700 | F10: 1001056900 | G10: NULL | H10: 1001056900 | I10: =VLOOKUP(H10,Swathi!L$1:L$1765,1,FALSE) -> 1001056900 | J10: In Swathi's report | K10: 53379832 | L10: NULL
A11: 83502 | B11: Dental | C11: 2025 | D11: 2025 | E11: 1008308 | F11: 1000975819 | G11: NULL | H11: 1000975819 | I11: =VLOOKUP(H11,Swathi!L$1:L$1765,1,FALSE) -> #N/A | J11: Not in Swathi's report | K11: 53379832 | L11: NULL
A12: 83502 | B12: Dental | C12: 2025 | D12: 2025 | E12: 10090369 | F12: 1001373500 | G12: NULL | H12: 1001373500 | I12: =VLOOKUP(H12,Swathi!L$1:L$1765,1,FALSE) -> #N/A | J12: Not in Swathi's report | K12: 53379832 | L12: NULL
A13: 83502 | B13: Dental | C13: 2025 | D13: 2025 | E13: 1009307 | F13: 1000666341 | G13: NULL | H13: 1000666341 | I13: =VLOOKUP(H13,Swathi!L$1:L$1765,1,FALSE) -> #N/A | J13: Not in Swathi's report | K13: 53379832 | L13: NULL
A14: 83502 | B14: Dental | C14: 2025 | D14: 2025 | E14: 1011230 | F14: 1001440431 | G14: NULL | H14: 1001440431 | I14: =VLOOKUP(H14,Swathi!L$1:L$1765,1,FALSE) -> #N/A | J14: Not in Swathi's report | K14: 53379832 | L14: NULL
A15: 83502 | B15: Dental | C15: 2025 | D15: 2025 | E15: 1013402 | F15: 1000140424 | G15: NULL | H15: 1000140424 | I15: =VLOOKUP(H15,Swathi!L$1:L$1765,1,FALSE) -> #N/A | J15: Not in Swathi's report | K15: 53379832 | L15: NULL
A16: 83502 | B16: Dental | C16: 2025 | D16: 2025 | E16: 1014254 | F16: 1001563044 | G16: NULL | H16: 1001563044 | I16: =VLOOKUP(H16,Swathi!L$1:L$1765,1,FALSE) -> #N/A | J16: Not in Swathi's report | K16: 53379832 | L16: NULL
A17: 83502 | B17: Dental | C17: 2025 | D17: 2025 | E17: 1019265 | F17: 1000416363 | G17: 107986004 | H17: 1000416363 | I17: =VLOOKUP(H17,Swathi!L$1:L$1765,1,FALSE) -> 1000416363 | J17: In Swathi's report | K17: 107986004 | L17: NULL
A18: 83502 | B18: Dental | C18: 2025 | D18: 2025 | E18: 10201347 | F18: 1001086740 | G18: NULL | H18: 1001086740 | I18: =VLOOKUP(H18,Swathi!L$1:L$1765,1,FALSE) -> #N/A | J18: Not in Swathi's report | K18: 53379832 | L18: NULL
A19: 83502 | B19: Dental | C19: 2025 | D19: 2025 | E19: 1022256 | F19: 1001000383 | G19: NULL | H19: 1001000383 | I19: =VLOOKUP(H19,Swathi!L$1:L$1765,1,FALSE) -> #N/A | J19: Not in Swathi's report | K19: 53379832 | L19: NULL
A20: 83502 | B20: Dental | C20: 2025 | D20: 2025 | E20: 1024335 | F20: 1000909226 | G20: 105009068 | H20: 1000909226 | I20: =VLOOKUP(H20,Swathi!L$1:L$1765,1,FALSE) -> 1000909226 | J20: In Swathi's report | K20: 105009068 | L20: NULL
A21: 83502 | B21: Dental | C21: 2025 | D21: 2025 | E21: 1025486 | F21: 1000872961 | G21: 109668296 | H21: 1000872961 | I21: =VLOOKUP(H21,Swathi!L$1:L$1765,1,FALSE) -> #N/A | J21: Not in Swathi's report | K21: 109668296 | L21: NULL
A22: 83502 | B22: Dental | C22: 2025 | D22: 2025 | E22: 1025486 | F22: 1000872961 | G22: NULL | H22: 1000872961 | I22: =VLOOKUP(H22,Swathi!L$1:L$1765,1,FALSE) -> #N/A | J22: Not in Swathi's report | K22: 53379832 | L22: NULL
A23: 83502 | B23: Dental | C23: 2025 | D23: 2025 | E23: 1027446 | F23: 1000643099 | G23: NULL | H23: 1000643099 | I23: =VLOOKUP(H23,Swathi!L$1:L$1765,1,FALSE) -> #N/A | J23: Not in Swathi's report | K23: 53379832 | L23: NULL
A24: 83502 | B24: Dental | C24: 2025 | D24: 2025 | E24: 1027668 | F24: 1001261233 | G24: NULL | H24: 1001261233 | I24: =VLOOKUP(H24,Swathi!L$1:L$1765,1,FALSE) -> #N/A | J24: Not in Swathi's report | K24: 53379832 | L24: NULL
A25: 83502 | B25: Dental | C25: 2025 | D25: 2025 | E25: 1031308 | F25: 1000171756 | G25: 110769429 | H25: 1000171756 | I25: =VLOOKUP(H25,Swathi!L$1:L$1765,1,FALSE) -> 1000171756 | J25: In Swathi's report | K25: 110769429 | L25: NULL
A26: 83502 | B26: Dental | C26: 2025 | D26: 2025 | E26: 103256 | F26: 1001643645 | G26: 110307900 | H26: 1001643645 | I26: =VLOOKUP(H26,Swathi!L$1:L$1765,1,FALSE) -> 1001643645 | J26: In Swathi's report | K26: 110307900 | L26: NULL
A27: 83502 | B27: Dental | C27: 2025 | D27: 2025 | E27: 103256 | F27: 1001643655 | G27: 110307900 | H27: 1001643655 | I27: =VLOOKUP(H27,Swathi!L$1:L$1765,1,FALSE) -> 1001643655 | J27: In Swathi's report | K27: 445936 | L27: NULL
A28: 83502 | B28: Dental | C28: 2025 | D28: 2025 | E28: 1033306 | F28: 1001376779 | G28: NULL | H28: 1001376779 | I28: =VLOOKUP(H28,Swathi!L$1:L$1765,1,FALSE) -> 1001376779 | J28: In Swathi's report | K28: 53379832 | L28: NULL
A29: 83502 | B29: Dental | C29: 2025 | D29: 2025 | E29: 1033306 | F29: 1001376779 | G29: NULL | H29: 1001376779 | I29: =VLOOKUP(H29,Swathi!L$1:L$1765,1,FALSE) -> 1001376779 | J29: In Swathi's report | K29: 53379832 | L29: NULL
A30: 83502 | B30: Dental | C30: 2025 | D30: 2025 | E30: 1033306 | F30: 1001376779 | G30: NULL | H30: 1001376779 | I30: =VLOOKUP(H30,Swathi!L$1:L$1765,1,FALSE) -> 1001376779 | J30: In Swathi's report | K30: 53379832 | L30: NULL
A31: 83502 | B31: Dental | C31: 2025 | D31: 2025 | E31: 1033391 | F31: 1000554435 | G31: 110497412 | H31: 1000554435 | I31: =VLOOKUP(H31,Swathi!L$1:L$1765,1,FALSE) -> 1000554435 | J31: In Swathi's report | K31: 110497412 | L31: NULL
A32: 83502 | B32: Dental | C32: 2025 | D32: 2025 | E32: 103357 | F32: 1000577674 | G32: NULL | H32: 1000577674 | I32: =VLOOKUP(H32,Swathi!L$1:L$1765,1,FALSE) -> #N/A | J32: Not in Swathi's report | K32: 53379832 | L32: NULL
A33: 83502 | B33: Dental | C33: 2025 | D33: 2025 | E33: 103371 | F33: 1000609907 | G33: NULL | H33: 1000609907 | I33: =VLOOKUP(H33,Swathi!L$1:L$1765,1,FALSE) -> #N/A | J33: Not in Swathi's report | K33: 53379832 | L33: NULL
A34: 83502 | B34: Dental | C34: 2025 | D34: 2025 | E34: 10339338 | F34: 1001725424 | G34: 110893278 | H34: 1001725424 | I34: =VLOOKUP(H34,Swathi!L$1:L$1765,1,FALSE) -> 1001725424 | J34: In Swathi's report | K34: 110893278 | L34: NULL
A35: 83502 | B35: Dental | C35: 2025 | D35: 2025 | E35: 1036339 | F35: 1000725287 | G35: NULL | H35: 1000725287 | I35: =VLOOKUP(H35,Swathi!L$1:L$1765,1,FALSE) -> #N/A | J35: Not in Swathi's report | K35: 53379832 | L35: NULL
A36: 83502 | B36: Dental | C36: 2025 | D36: 2025 | E36: 1039719 | F36: 1000426411 | G36: 110260831 | H36: 1000426411 | I36: =VLOOKUP(H36,Swathi!L$1:L$1765,1,FALSE) -> 1000426411 | J36: In Swathi's report | K36: 110260831 | L36: NULL
A37: 83502 | B37: Dental | C37: 2025 | D37: 2025 | E37: 1039719 | F37: 1000426412 | G37: 110260831 | H37: 1000426412 | I37: =VLOOKUP(H37,Swathi!L$1:L$1765,1,FALSE) -> 1000426412 | J37: In Swathi's report | K37: 443990 | L37: NULL
A38: 83502 | B38: Dental | C38: 2025 | D38: 2025 | E38: 1039788 | F38: 1000804700 | G38: NULL | H38: 1000804700 | I38: =VLOOKUP(H38,Swathi!L$1:L$1765,1,FALSE) -> #N/A | J38: Not in Swathi's report | K38: 53379832 | L38: NULL
A39: 83502 | B39: Dental | C39: 2025 | D39: 2025 | E39: 1041310 | F39: 1000765192 | G39: NULL | H39: 1000765192 | I39: =VLOOKUP(H39,Swathi!L$1:L$1765,1,FALSE) -> #N/A | J39: Not in Swathi's report | K39: 53379832 | L39: NULL
A40: 83502 | B40: Dental | C40: 2025 | D40: 2025 | E40: 1046279 | F40: 1000388290 | G40: NULL | H40: 1000388290 | I40: =VLOOKUP(H40,Swathi!L$1:L$1765,1,FALSE) -> #N/A | J40: Not in Swathi's report | K40: 53379832 | L40: NULL
A41: 83502 | B41: Dental | C41: 2025 | D41: 2025 | E41: 1046565 | F41: 1000355133 | G41: 110475444 | H41: 1000355133 | I41: =VLOOKUP(H41,Swathi!L$1:L$1765,1,FALSE) -> 1000355133 | J41: In Swathi's report | K41: 110475444 | L41: NULL
A42: 83502 | B42: Dental | C42: 2025 | D42: 2025 | E42: 1046565 | F42: 1000355192 | G42: 110475444 | H42: 1000355192 | I42: =VLOOKUP(H42,Swathi!L$1:L$1765,1,FALSE) -> 1000355192 | J42: In Swathi's report | K42: 452663 | L42: NULL
A43: 83502 | B43: Dental | C43: 2025 | D43: 2025 | E43: 10467448 | F43: 1000899689 | G43: NULL | H43: 1000899689 | I43: =VLOOKUP(H43,Swathi!L$1:L$1765,1,FALSE) -> #N/A | J43: Not in Swathi's report | K43: 53379832 | L43: NULL
A44: 83502 | B44: Dental | C44: 2025 | D44: 2025 | E44: 1047253 | F44: 1001320652 | G44: NULL | H44: 1001320652 | I44: =VLOOKUP(H44,Swathi!L$1:L$1765,1,FALSE) -> #N/A | J44: Not in Swathi's report | K44: 53379832 | L44: NULL
A45: 83502 | B45: Dental | C45: 2025 | D45: 2025 | E45: 105987 | F45: 1000112033 | G45: 109704018 | H45: 1000112033 | I45: =VLOOKUP(H45,Swathi!L$1:L$1765,1,FALSE) -> #N/A | J45: Not in Swathi's report | K45: 109704018 | L45: NULL
A46: 83502 | B46: Dental | C46: 2025 | D46: 2025 | E46: 105987 | F46: 1000112034 | G46: 109704018 | H46: 1000112034 | I46: =VLOOKUP(H46,Swathi!L$1:L$1765,1,FALSE) -> #N/A | J46: Not in Swathi's report | K46: 421251 | L46: NULL
A47: 83502 | B47: Dental | C47: 2025 | D47: 2025 | E47: 105998 | F47: 1001379914 | G47: 110032246 | H47: 1001379914 | I47: =VLOOKUP(H47,Swathi!L$1:L$1765,1,FALSE) -> 1001379914 | J47: In Swathi's report | K47: 110032246 | L47: NULL
A48: 83502 | B48: Dental | C48: 2025 | D48: 2025 | E48: 106947 | F48: 1001202204 | G48: 110683021 | H48: 1001202204 | I48: =VLOOKUP(H48,Swathi!L$1:L$1765,1,FALSE) -> 1001202204 | J48: In Swathi's report | K48: 110683021 | L48: NULL
A49: 83502 | B49: Dental | C49: 2025 | D49: 2025 | E49: 106958 | F49: 1001551075 | G49: 105356512 | H49: 1001551075 | I49: =VLOOKUP(H49,Swathi!L$1:L$1765,1,FALSE) -> 1001551075 | J49: In Swathi's report | K49: 105356512 | L49: NULL
A50: 83502 | B50: Dental | C50: 2025 | D50: 2025 | E50: 106958 | F50: 1001551075 | G50: NULL | H50: 1001551075 | I50: =VLOOKUP(H50,Swathi!L$1:L$1765,1,FALSE) -> 1001551075 | J50: In Swathi's report | K50: 53379832 | L50: NULL
A51: 83502 | B51: Dental | C51: 2025 | D51: 2025 | E51: 106958 | F51: 1001551081 | G51: 105356512 | H51: 1001551081 | I51: =VLOOKUP(H51,Swathi!L$1:L$1765,1,FALSE) -> 1001551081 | J51: In Swathi's report | K51: 254043 | L51: NULL
A52: 83502 | B52: Dental | C52: 2025 | D52: 2025 | E52: 106958 | F52: 1001551084 | G52: 105356512 | H52: 1001551084 | I52: =VLOOKUP(H52,Swathi!L$1:L$1765,1,FALSE) -> #N/A | J52: Not in Swathi's report | K52: 465211 | L52: NULL
A53: 83502 | B53: Dental | C53: 2025 | D53: 2025 | E53: 106985 | F53: 1000277937 | G53: 110301548 | H53: 1000277937 | I53: =VLOOKUP(H53,Swathi!L$1:L$1765,1,FALSE) -> 1000277937 | J53: In Swathi's report | K53: 110301548 | L53: NULL
A54: 83502 | B54: Dental | C54: 2025 | D54: 2025 | E54: 107163 | F54: 1000277936 | G54: 110301556 | H54: 1000277936 | I54: =VLOOKUP(H54,Swathi!L$1:L$1765,1,FALSE) -> 1000277936 | J54: In Swathi's report | K54: 110301556 | L54: NULL
A55: 83502 | B55: Dental | C55: 2025 | D55: 2025 | E55: 1078130 | F55: 1001549268 | G55: 109710019 | H55: 1001549268 | I55: =VLOOKUP(H55,Swathi!L$1:L$1765,1,FALSE) -> 1001549268 | J55: In Swathi's report | K55: 109710019 | L55: NULL
A56: 83502 | B56: Dental | C56: 2025 | D56: 2025 | E56: 1078130 | F56: 1001549270 | G56: 109710019 | H56: 1001549270 | I56: =VLOOKUP(H56,Swathi!L$1:L$1765,1,FALSE) -> #N/A | J56: Not in Swathi's report | K56: 435481 | L56: NULL
A57: 83502 | B57: Dental | C57: 2025 | D57: 2025 | E57: 109504 | F57: 1000737015 | G57: 108918957 | H57: 1000737015 | I57: =VLOOKUP(H57,Swathi!L$1:L$1765,1,FALSE) -> 1000737015 | J57: In Swathi's report | K57: 108918957 | L57: NULL
A58: 83502 | B58: Dental | C58: 2025 | D58: 2025 | E58: 109958 | F58: 1001440356 | G58: NULL | H58: 1001440356 | I58: =VLOOKUP(H58,Swathi!L$1:L$1765,1,FALSE) -> #N/A | J58: Not in Swathi's report | K58: 53379832 | L58: NULL
A59: 83502 | B59: Dental | C59: 2025 | D59: 2025 | E59: 109958 | F59: 1001440356 | G59: 110127601 | H59: 1001440356 | I59: =VLOOKUP(H59,Swathi!L$1:L$1765,1,FALSE) -> #N/A | J59: Not in Swathi's report | K59: 110127601 | L59: NULL
A60: 83502 | B60: Dental | C60: 2025 | D60: 2025 | E60: 1100092 | F60: 1000621895 | G60: NULL | H60: 1000621895 | I60: =VLOOKUP(H60,Swathi!L$1:L$1765,1,FALSE) -> #N/A | J60: Not in Swathi's report | K60: 53379832 | L60: NULL
A61: 83502 | B61: Dental | C61: 2025 | D61: 2025 | E61: 11084559 | F61: 1000207725 | G61: NULL | H61: 1000207725 | I61: =VLOOKUP(H61,Swathi!L$1:L$1765,1,FALSE) -> #N/A | J61: Not in Swathi's report | K61: 53379832 | L61: NULL
A62: 83502 | B62: Dental | C62: 2025 | D62: 2025 | E62: 11115558 | F62: 1001832083 | G62: NULL | H62: 1001832083 | I62: =VLOOKUP(H62,Swathi!L$1:L$1765,1,FALSE) -> #N/A | J62: Not in Swathi's report | K62: 53379832 | L62: NULL
A63: 83502 | B63: Dental | C63: 2025 | D63: 2025 | E63: 111271 | F63: 1000356119 | G63: 110513187 | H63: 1000356119 | I63: =VLOOKUP(H63,Swathi!L$1:L$1765,1,FALSE) -> 1000356119 | J63: In Swathi's report | K63: 110513187 | L63: NULL
A64: 83502 | B64: Dental | C64: 2025 | D64: 2025 | E64: 11156563 | F64: 1001833948 | G64: NULL | H64: 1001833948 | I64: =VLOOKUP(H64,Swathi!L$1:L$1765,1,FALSE) -> #N/A | J64: Not in Swathi's report | K64: 53379832 | L64: NULL
A65: 83502 | B65: Dental | C65: 2025 | D65: 2025 | E65: 11184566 | F65: 1000319929 | G65: NULL | H65: 1000319929 | I65: =VLOOKUP(H65,Swathi!L$1:L$1765,1,FALSE) -> 1000319929 | J65: In Swathi's report | K65: 53379832 | L65: NULL
A66: 83502 | B66: Dental | C66: 2025 | D66: 2025 | E66: 11219570 | F66: 1001841457 | G66: NULL | H66: 1001841457 | I66: =VLOOKUP(H66,Swathi!L$1:L$1765,1,FALSE) -> #N/A | J66: Not in Swathi's report | K66: 53379832 | L66: NULL
A67: 83502 | B67: Dental | C67: 2025 | D67: 2025 | E67: 11243567 | F67: 1001850459 | G67: 110432098 | H67: 1001850459 | I67: =VLOOKUP(H67,Swathi!L$1:L$1765,1,FALSE) -> 1001850459 | J67: In Swathi's report | K67: 110432098 | L67: NULL
A68: 83502 | B68: Dental | C68: 2025 | D68: 2025 | E68: 11243567 | F68: 1001850459 | G68: NULL | H68: 1001850459 | I68: =VLOOKUP(H68,Swathi!L$1:L$1765,1,FALSE) -> 1001850459 | J68: In Swathi's report | K68: 53379832 | L68: NULL
A69: 83502 | B69: Dental | C69: 2025 | D69: 2025 | E69: 1128096 | F69: 1000144528 | G69: 109617596 | H69: 1000144528 | I69: =VLOOKUP(H69,Swathi!L$1:L$1765,1,FALSE) -> #N/A | J69: Not in Swathi's report | K69: 109617596 | L69: NULL
A70: 83502 | B70: Dental | C70: 2025 | D70: 2025 | E70: 1128096 | F70: 1000144528 | G70: NULL | H70: 1000144528 | I70: =VLOOKUP(H70,Swathi!L$1:L$1765,1,FALSE) -> #N/A | J70: Not in Swathi's report | K70: 53379832 | L70: NULL
A71: 83502 | B71: Dental | C71: 2025 | D71: 2025 | E71: 113181 | F71: 1000225978 | G71: NULL | H71: 1000225978 | I71: =VLOOKUP(H71,Swathi!L$1:L$1765,1,FALSE) -> #N/A | J71: Not in Swathi's report | K71: 53379832 | L71: NULL
A72: 83502 | B72: Dental | C72: 2025 | D72: 2025 | E72: 113181 | F72: 1000225978 | G72: 109421505 | H72: 1000225978 | I72: =VLOOKUP(H72,Swathi!L$1:L$1765,1,FALSE) -> #N/A | J72: Not in Swathi's report | K72: 109421505 | L72: NULL
A73: 83502 | B73: Dental | C73: 2025 | D73: 2025 | E73: 113202 | F73: 1001306914 | G73: 110386124 | H73: 1001306914 | I73: =VLOOKUP(H73,Swathi!L$1:L$1765,1,FALSE) -> #N/A | J73: Not in Swathi's report | K73: 448965 | L73: NULL
A74: 83502 | B74: Dental | C74: 2025 | D74: 2025 | E74: 113202 | F74: 1001306915 | G74: 110386124 | H74: 1001306915 | I74: =VLOOKUP(H74,Swathi!L$1:L$1765,1,FALSE) -> #N/A | J74: Not in Swathi's report | K74: 110386124 | L74: NULL
A75: 83502 | B75: Dental | C75: 2025 | D75: 2025 | E75: 113831 | F75: 1001391184 | G75: NULL | H75: 1001391184 | I75: =VLOOKUP(H75,Swathi!L$1:L$1765,1,FALSE) -> #N/A | J75: Not in Swathi's report | K75: 53379832 | L75: NULL
A76: 83502 | B76: Dental | C76: 2025 | D76: 2025 | E76: 113861 | F76: 1000151918 | G76: NULL | H76: 1000151918 | I76: =VLOOKUP(H76,Swathi!L$1:L$1765,1,FALSE) -> #N/A | J76: Not in Swathi's report | K76: 53379832 | L76: NULL
A77: 83502 | B77: Dental | C77: 2025 | D77: 2025 | E77: 11415575 | F77: 1000006950 | G77: NULL | H77: 1000006950 | I77: =VLOOKUP(H77,Swathi!L$1:L$1765,1,FALSE) -> #N/A | J77: Not in Swathi's report | K77: 53379832 | L77: NULL
A78: 83502 | B78: Dental | C78: 2025 | D78: 2025 | E78: 11420580 | F78: 1000603217 | G78: 110282443 | H78: 1000603217 | I78: =VLOOKUP(H78,Swathi!L$1:L$1765,1,FALSE) -> #N/A | J78: Not in Swathi's report | K78: 110282443 | L78: NULL
A79: 83502 | B79: Dental | C79: 2025 | D79: 2025 | E79: 11435583 | F79: 1000550578 | G79: 110360592 | H79: 1000550578 | I79: =VLOOKUP(H79,Swathi!L$1:L$1765,1,FALSE) -> #N/A | J79: Not in Swathi's report | K79: 110360592 | L79: NULL
A80: 83502 | B80: Dental | C80: 2025 | D80: 2025 | E80: 11435583 | F80: 1000550579 | G80: 110360592 | H80: 1000550579 | I80: =VLOOKUP(H80,Swathi!L$1:L$1765,1,FALSE) -> #N/A | J80: Not in Swathi's report | K80: 448003 | L80: NULL
A81: 83502 | B81: Dental | C81: 2025 | D81: 2025 | E81: 11457569 | F81: 1001510405 | G81: 110394680 | H81: 1001510405 | I81: =VLOOKUP(H81,Swathi!L$1:L$1765,1,FALSE) -> 1001510405 | J81: In Swathi's report | K81: 110394680 | L81: NULL
A82: 83502 | B82: Dental | C82: 2025 | D82: 2025 | E82: 11457569 | F82: 1001510406 | G82: 110394680 | H82: 1001510406 | I82: =VLOOKUP(H82,Swathi!L$1:L$1765,1,FALSE) -> 1001510406 | J82: In Swathi's report | K82: 449336 | L82: NULL
A83: 83502 | B83: Dental | C83: 2025 | D83: 2025 | E83: 11457569 | F83: 1001510407 | G83: 110394680 | H83: 1001510407 | I83: =VLOOKUP(H83,Swathi!L$1:L$1765,1,FALSE) -> 1001510407 | J83: In Swathi's report | K83: 466591 | L83: NULL
A84: 83502 | B84: Dental | C84: 2025 | D84: 2025 | E84: 11457569 | F84: 1001510408 | G84: 110394680 | H84: 1001510408 | I84: =VLOOKUP(H84,Swathi!L$1:L$1765,1,FALSE) -> 1001510408 | J84: In Swathi's report | K84: 466592 | L84: NULL
A85: 83502 | B85: Dental | C85: 2025 | D85: 2025 | E85: 114759 | F85: 1000034371 | G85: NULL | H85: 1000034371 | I85: =VLOOKUP(H85,Swathi!L$1:L$1765,1,FALSE) -> #N/A | J85: Not in Swathi's report | K85: 53379832 | L85: NULL
A86: 83502 | B86: Dental | C86: 2025 | D86: 2025 | E86: 114784 | F86: 1000907375 | G86: NULL | H86: 1000907375 | I86: =VLOOKUP(H86,Swathi!L$1:L$1765,1,FALSE) -> #N/A | J86: Not in Swathi's report | K86: 53379832 | L86: NULL
A87: 83502 | B87: Dental | C87: 2025 | D87: 2025 | E87: 11514586 | F87: 1001857981 | G87: NULL | H87: 1001857981 | I87: =VLOOKUP(H87,Swathi!L$1:L$1765,1,FALSE) -> #N/A | J87: Not in Swathi's report | K87: 53379832 | L87: NULL
A88: 83502 | B88: Dental | C88: 2025 | D88: 2025 | E88: 115486 | F88: 1000010809 | G88: 104289657 | H88: 1000010809 | I88: =VLOOKUP(H88,Swathi!L$1:L$1765,1,FALSE) -> 1000010809 | J88: In Swathi's report | K88: 104289657 | L88: NULL
A89: 83502 | B89: Dental | C89: 2025 | D89: 2025 | E89: 116808 | F89: 1001454901 | G89: 110317688 | H89: 1001454901 | I89: =VLOOKUP(H89,Swathi!L$1:L$1765,1,FALSE) -> #N/A | J89: Not in Swathi's report | K89: 110317688 | L89: NULL
A90: 83502 | B90: Dental | C90: 2025 | D90: 2025 | E90: 116808 | F90: 1001454901 | G90: NULL | H90: 1001454901 | I90: =VLOOKUP(H90,Swathi!L$1:L$1765,1,FALSE) -> #N/A | J90: Not in Swathi's report | K90: 53379832 | L90: NULL
A91: 83502 | B91: Dental | C91: 2025 | D91: 2025 | E91: 1173104 | F91: 1001281582 | G91: 110360835 | H91: 1001281582 | I91: =VLOOKUP(H91,Swathi!L$1:L$1765,1,FALSE) -> #N/A | J91: Not in Swathi's report | K91: 110360835 | L91: NULL
A92: 83502 | B92: Dental | C92: 2025 | D92: 2025 | E92: 1180173 | F92: 1001158262 | G92: 110365225 | H92: 1001158262 | I92: =VLOOKUP(H92,Swathi!L$1:L$1765,1,FALSE) -> 1001158262 | J92: In Swathi's report | K92: 110365225 | L92: NULL
A93: 83502 | B93: Dental | C93: 2025 | D93: 2025 | E93: 118024 | F93: 1001296473 | G93: 109143872 | H93: 1001296473 | I93: =VLOOKUP(H93,Swathi!L$1:L$1765,1,FALSE) -> 1001296473 | J93: In Swathi's report | K93: 109143872 | L93: NULL
A94: 83502 | B94: Dental | C94: 2025 | D94: 2025 | E94: 118024 | F94: 1001296474 | G94: 109143872 | H94: 1001296474 | I94: =VLOOKUP(H94,Swathi!L$1:L$1765,1,FALSE) -> 1001296474 | J94: In Swathi's report | K94: 398711 | L94: NULL
A95: 83502 | B95: Dental | C95: 2025 | D95: 2025 | E95: 1180424 | F95: 1000777146 | G95: 110346881 | H95: 1000777146 | I95: =VLOOKUP(H95,Swathi!L$1:L$1765,1,FALSE) -> 1000777146 | J95: In Swathi's report | K95: 110346881 | L95: NULL
A96: 83502 | B96: Dental | C96: 2025 | D96: 2025 | E96: 118287 | F96: 1001580060 | G96: NULL | H96: 1001580060 | I96: =VLOOKUP(H96,Swathi!L$1:L$1765,1,FALSE) -> #N/A | J96: Not in Swathi's report | K96: 53379832 | L96: NULL
A97: 83502 | B97: Dental | C97: 2025 | D97: 2025 | E97: 118404 | F97: 1001534577 | G97: NULL | H97: 1001534577 | I97: =VLOOKUP(H97,Swathi!L$1:L$1765,1,FALSE) -> 1001534577 | J97: In Swathi's report | K97: 53379832 | L97: NULL
A98: 83502 | B98: Dental | C98: 2025 | D98: 2025 | E98: 118404 | F98: 1001534577 | G98: NULL | H98: 1001534577 | I98: =VLOOKUP(H98,Swathi!L$1:L$1765,1,FALSE) -> 1001534577 | J98: In Swathi's report | K98: 53379832 | L98: NULL
A99: 83502 | B99: Dental | C99: 2025 | D99: 2025 | E99: 118404 | F99: 1001534577 | G99: NULL | H99: 1001534577 | I99: =VLOOKUP(H99,Swathi!L$1:L$1765,1,FALSE) -> 1001534577 | J99: In Swathi's report | K99: 53379832 | L99: NULL
A100: 83502 | B100: Dental | C100: 2025 | D100: 2025 | E100: 119039 | F100: 1001492698 | G100: NULL | H100: 1001492698 | I100: =VLOOKUP(H100,Swathi!L$1:L$1765,1,FALSE) -> #N/A | J100: Not in Swathi's report | K100: 53379832 | L100: NULL
...
